public final class c extends fl {
  private byte bv = 0;
  
  public static byte a = 0;
  
  public static byte b = 1;
  
  public static byte c = 2;
  
  public static byte d = 3;
  
  public static byte e = 4;
  
  public static byte f = 5;
  
  public static byte g = 6;
  
  private static byte bw = 0;
  
  private static byte bx = 1;
  
  private static byte by = 2;
  
  public static String[] h = new String[] { "", "", "", "", "" };
  
  public static byte[] i = new byte[5];
  
  private int bz;
  
  private int bA;
  
  private int bB = 12;
  
  private int bC = 140;
  
  private int[][] bD;
  
  public static String[] j;
  
  private int bE;
  
  private int bF;
  
  public static b[] k;
  
  public static j l;
  
  public static j m;
  
  public static j n;
  
  public static j o;
  
  public static int[] p;
  
  public static short[] q;
  
  public static int[] r;
  
  public static b[] s;
  
  public static int t = 0;
  
  public static int u;
  
  public static String v = "";
  
  public static int w = 0;
  
  public static short x = 0;
  
  public static short y = 0;
  
  public static String z = "test nao";
  
  public static String A;
  
  public static byte B = 0;
  
  public static byte C = 0;
  
  public static boolean D = false;
  
  private static boolean bG;
  
  private bt bH;
  
  private bt bI;
  
  private bt bJ;
  
  private bt bK;
  
  private bt bL;
  
  public static es E = new es("TabRebuildItem vecEffRe");
  
  public static String F = "";
  
  private es bM = new es("TabRebuildItem vecListCmd");
  
  public static es G = new es("TabRebuildItem vecGem");
  
  public static boolean H = false;
  
  private static boolean bN = false;
  
  private fz bO = new fz();
  
  public static bw I = null;
  
  private int bP;
  
  private long bQ;
  
  public static byte J = 0;
  
  public c(String paramString, byte paramByte) {
    bN = false;
    this.bb = false;
    this.ba = null;
    this.bv = paramByte;
    this.K = 10;
    this.X = paramString;
    this.V = this.L + fl.aM + fl.aN * 3;
    this.W = 0 + ft.X / 5 + fl.aM;
    this.bz = (fl.S - 8) / 32;
    this.bA = (fl.T - 8) / 32;
    if (fl.aU > 0) {
      this.bC = fl.aU;
      this.bE = fl.aV;
      this.bF = fl.aW + fl.aM / 2;
    } else {
      this.bE = this.V + fl.S / 2 - this.bC / 2;
      this.bF = this.W + 4;
      if (this.bF > ft.X - ft.aa - 150 - ft.aa)
        this.bF = ft.X - ft.aa - 150 - ft.aa; 
    } 
    if (ft.C)
      this.bF = ft.X - ft.aa - 150 - ft.aa; 
    this.aT = new bt(df.af, -1, this);
    this.bI = new bt(df.bK, 1, this);
    if (ft.A)
      this.aT.a = df.Z; 
    if (this.bv == 0 || this.bv == d || this.bv == f || this.bv == e || this.bv == g) {
      this.bD = dw.a(6, 2);
      this.bD[4][0] = this.V + fl.S / 2;
      this.bD[4][1] = this.W + fl.T / 2 - 52;
      this.bD[2][0] = this.V + fl.S / 2 + 52;
      this.bD[2][1] = this.W + fl.T / 2 - 16;
      this.bD[1][0] = this.V + fl.S / 2 + 32;
      this.bD[1][1] = this.W + fl.T / 2 + 45;
      this.bD[3][0] = this.V + fl.S / 2 - 32;
      this.bD[3][1] = this.W + fl.T / 2 + 45;
      this.bD[0][0] = this.V + fl.S / 2 - 52;
      this.bD[0][1] = this.W + fl.T / 2 - 16;
      this.bD[5][0] = this.V + fl.S / 2;
      this.bD[5][1] = this.W + fl.T / 2;
      D = false;
      this.Z = null;
      bG = false;
      this.bH = new bt(df.eg, 0, this);
      this.bL = new bt(df.h, 9, this);
      if (fl.aU > 0) {
        int i = fl.aW + this.N;
        int k = fl.aV;
        if (fl.aZ) {
          this.bH.a(k + fl.aU / 2, i - 10, cf.v, this.bH.a);
          this.bL.a(k + fl.aU / 2, i - 10, cf.v, this.bL.a);
        } else {
          this.bH.a(k + fl.aU / 2, i - 15, (ce)null, this.bH.a);
          this.bL.a(k + fl.aU / 2, i - 15, (ce)null, this.bL.a);
        } 
      } else if (ft.A) {
        this.bH.a(bt.j / 2 + 2, ft.X - bt.k / 2 - 2, (ce)null, this.bH.a);
        this.bL.a(bt.j / 2 + 2, ft.X - bt.k / 2 - 2, (ce)null, this.bL.a);
        this.bI.a(ft.W - bt.j / 2 - 2, ft.X - bt.k / 2 - 2, (ce)null, this.bI.a);
      } 
    } else if (this.bv == b) {
      this.bD = dw.a(2, 2);
      this.bD[1][0] = this.V + fl.S / 2 + 52;
      this.bD[1][1] = this.W + fl.T / 2 - 16;
      this.bD[0][0] = this.V + fl.S / 2 - 52;
      this.bD[0][1] = this.W + fl.T / 2 - 16;
      this.bJ = new bt(df.fk, 3, this);
      if (fl.aU > 0) {
        int i = fl.aW + this.N;
        int k = fl.aV;
        if (fl.aZ) {
          this.bJ.a(k + fl.aU / 2, i - 10, cf.v, this.bJ.a);
        } else {
          this.bJ.a(k + fl.aU / 2, i - 15, (ce)null, this.bJ.a);
        } 
      } else if (ft.A) {
        this.bJ.a(bt.j / 2 + 2, ft.X - bt.k / 2 - 2, (ce)null, this.bJ.a);
        this.bI.a(ft.W - bt.j / 2 - 2, ft.X - bt.k / 2 - 2, (ce)null, this.bI.a);
      } 
    } else if (this.bv == c) {
      this.bD = dw.a(7, 2);
      this.bD[1][0] = this.V + fl.S / 2;
      this.bD[1][1] = this.W + fl.T / 2 - 52;
      this.bD[5][0] = this.V + fl.S / 2 + 46;
      this.bD[5][1] = this.W + fl.T / 2 - 26;
      this.bD[2][0] = this.V + fl.S / 2 + 46;
      this.bD[2][1] = this.W + fl.T / 2 + 26;
      this.bD[4][0] = this.V + fl.S / 2;
      this.bD[4][1] = this.W + fl.T / 2 + 52;
      this.bD[0][0] = this.V + fl.S / 2 - 46;
      this.bD[0][1] = this.W + fl.T / 2 + 26;
      this.bD[3][0] = this.V + fl.S / 2 - 46;
      this.bD[3][1] = this.W + fl.T / 2 - 26;
      this.bD[6][0] = this.V + fl.S / 2;
      this.bD[6][1] = this.W + fl.T / 2;
      this.bK = new bt(df.fx, 4, this);
      if (fl.aU > 0) {
        int i = fl.aW + this.N;
        int k = fl.aV;
        if (fl.aZ) {
          this.bK.a(k + fl.aU / 2, i - 10, cf.v, this.bK.a);
        } else {
          this.bK.a(k + fl.aU / 2, i - 15, (ce)null, this.bK.a);
        } 
      } else if (ft.A) {
        this.bK.a(bt.j / 2 + 2, ft.X - bt.k / 2 - 2, (ce)null, this.bK.a);
        this.bI.a(ft.W - bt.j / 2 - 2, ft.X - bt.k / 2 - 2, (ce)null, this.bI.a);
      } 
    } 
    b();
    if (this.bv == f || this.bv == e || this.bv == d || this.bv == 0 || this.bv == b || this.bv == g) {
      this.ba = aq.a("/interface/rebuild.img");
      return;
    } 
    if (this.bv == c)
      this.ba = aq.a("/interface/rebuild2.img"); 
  }
  
  private void f() {
    this.bj = null;
    this.bk = null;
    this.bl = null;
    if (l != null && l.g != null)
      this.bp = l.g; 
    this.aY = null;
    if (l != null) {
      int i = 1;
      this.bj = l.k;
      this.bu = l.J;
      this.bl = l.l;
      this.bo = l.n;
      this.bm = l.m;
      this.br = l.N;
      if (l.k != null)
        i = 1 + this.bj.length; 
      if (l.l != null)
        i += l.l.length; 
      if (i * ft.ab > fl.U - 30) {
        this.aY = new bp(fl.aV, fl.aW, fl.aU, fl.U, 0, 0, i * ft.ab - fl.U - 30);
        return;
      } 
      if (ft.A)
        this.aY = new bp(fl.aV, fl.aW, fl.aU, fl.U, 0, 0, 0); 
      return;
    } 
  }
  
  public final void a(int paramInt1, int paramInt2) {
    es es1;
    String str;
    switch (paramInt1) {
      case -1:
        c();
        break;
      case 0:
      case 9:
        if (paramInt1 == 9)
          bN = true; 
        if (this.bv == g) {
          if (this.be && l != null) {
            q.a().c((byte)4, (short)l.O, (byte)l.u);
            G.d();
            return;
          } 
          if (this.bd) {
            q.a().m((byte)3);
            G.d();
            break;
          } 
          if (G.c() > 0) {
            j j1;
            if ((j1 = (j)G.a(0)) != null) {
              q.a().c((byte)2, (short)j1.O, (byte)j1.u);
              G.d();
            } 
            break;
          } 
          ft.a(df.t);
          break;
        } 
        if (this.bv == f) {
          int i = -1;
          if (l != null && G.c() > 0) {
            j j1;
            if ((j1 = (j)G.a(0)) != null)
              i = j1.O; 
            q.a().a(by, l.O, i, -1, -1);
            break;
          } 
          ft.a(df.H);
          break;
        } 
        if (this.bv == e) {
          if (G.c() > 0) {
            j j1;
            if ((j1 = (j)G.a(0)) != null)
              q.a().a(bx, j1.O, -1, -1, -1); 
            break;
          } 
          ft.a(df.K);
          break;
        } 
        if (this.bv == d) {
          if (l != null && G.c() > 0) {
            int[] arrayOfInt = { -1, -1, -1 };
            for (byte b1 = 0; b1 < G.c(); b1++) {
              j j1;
              if ((j1 = (j)G.a(b1)) != null)
                arrayOfInt[b1] = j1.O; 
            } 
            q.a().a((byte)0, l.O, arrayOfInt[0], arrayOfInt[1], arrayOfInt[2]);
            break;
          } 
          ft.a(df.O);
          break;
        } 
        if (l != null) {
          String str1 = "";
          byte b1 = 0;
          es es2 = new es("TabRebuildItem menu");
          if ((k[l.z]).c != 0) {
            es2.a(new bt(df.bO, 2, 0, this));
            str1 = String.valueOf(df.ek) + j.a((k[l.z]).c) + " " + df.bO + "?";
            b1++;
          } 
          if ((k[l.z]).d != 0) {
            es2.a(new bt(df.bP, 2, 1, this));
            str1 = String.valueOf(df.ek) + (k[l.z]).d + " " + df.bP + "?";
            b1++;
          } 
          if (b1 == 2)
            str1 = String.valueOf(df.eh) + j.a((k[l.z]).c) + " " + df.bO + df.ei + (k[l.z]).d + " " + df.bP + "?"; 
          ft.o.a(es2, str1, fq.f, (byte)2, false, 0);
        } 
        break;
      case 1:
        if (fl.aU == 0) {
          if ((l != null && (this.bv == 0 || this.bv == d)) || (m != null && n != null && this.bv == b) || (this.bv == c && s != null) || this.bv == g) {
            bG = !bG;
          } else {
            bG = false;
          } 
          if (bG) {
            if (!ft.A) {
              this.bI.a = df.Z;
              break;
            } 
            this.bI.a(this.bE + this.bC - 12, this.bF + 10, cf.t, "");
            break;
          } 
          if (!ft.A) {
            this.bI.a = df.bK;
            break;
          } 
          this.bI.a = df.bK;
          this.bI.a(ft.W - bt.j / 2, ft.X - bt.k / 2, (ce)null, this.bI.a);
        } 
        break;
      case 2:
        if (l != null) {
          ft.o.f();
          q.a().b((byte)2, (short)0, (byte)paramInt2);
          if (fl.aU == 0) {
            bG = false;
            if (!ft.A) {
              this.bI.a = df.bK;
            } else {
              this.bI.a = df.bK;
              this.bI.a(ft.W - bt.j / 2, ft.X - bt.k / 2, (ce)null, this.bI.a);
            } 
          } 
          ft.a(df.aG, new bt(df.Z, -1));
        } 
        break;
      case 3:
        if (n != null && m != null) {
          q.a().b((byte)1, (short)0);
          ft.a(df.aG, new bt(df.Z, -1));
        } 
        break;
      case 4:
        es1 = new es("TabRebuildItem menu2");
        str = null;
        if (o == null) {
          str = String.valueOf(df.fw) + this.X + "? " + df.fj + ": " + j.a(t) + " " + df.bO + ", " + df.bG + x + ", " + df.fu + cf.a(u) + ".";
          es1.a(new bt(df.fv, 5, 0, this));
        } else {
          str = String.valueOf(df.fD) + v + "? " + df.fj + ": " + j.a(t) + " " + df.bO + ", " + df.bG + x + ", " + df.fu + cf.a(u) + ".";
          es1.a(new bt(df.fx, 6, 0, this));
        } 
        ft.o.a(es1, str, fq.f, (byte)2, false, 0);
        break;
      case 5:
        ft.o.f();
        q.a().a((byte)1, w, (short)0);
        break;
      case 6:
        ft.o.f();
        if (o != null)
          q.a().a((byte)3, w, (short)o.O); 
        break;
      case 7:
        ft.o.f();
        q.a().b((byte)5, (short)l.O, (byte)l.u);
        if (fl.aU == 0) {
          bG = false;
          if (!ft.A) {
            this.bI.a = df.bK;
          } else {
            this.bI.a = df.bK;
            this.bI.a(ft.W - bt.j / 2, ft.X - bt.k / 2, (ce)null, this.bI.a);
          } 
        } 
        ft.a(df.aG, new bt(df.Z, -1));
        break;
    } 
    super.a(paramInt1, paramInt2);
  }
  
  public final void b() {
    String str;
    this.bI.a = df.bK;
    if (this.bv == 0 || this.bv == d || this.bv == e || this.bv == f || this.bv == g) {
      this = this;
      bN = false;
      fl.bi = 0;
      if (fl.aU > 0)
        bG = true; 
      if (!ft.A) {
        if (l != null || this.bv == e || this.bv == g) {
          this.Y = this.bI;
          this.aa = this.bH;
        } 
        this.Z = this.aT;
      } else {
        this.bM.d();
        if (l != null)
          if (fl.aU > 0) {
            this.bM.a(this.bH);
          } else {
            this.bM.a(this.bI);
            this.bM.a(this.bH);
          }  
        if (this.bv == e) {
          this.bM.a(this.bH);
          this.bH.a = df.L;
        } 
        if (this.bv == g) {
          this.bM.a(this.bH);
          this.bH.a = df.s;
        } 
      } 
      this.aY = null;
      E.d();
      B = 0;
      C = 0;
      if (l == null && this.bv != e && this.bv != g) {
        str = this.bb ? df.gc : df.ej;
        ft.o.a(null, this, fq.f, (byte)2, false, 0);
      } 
      return;
    } 
    if (((c)super).bv == b) {
      str = this;
      fl.bi = 0;
      if (fl.aU > 0)
        bG = true; 
      if (!ft.A) {
        if (m != null && n != null && !H) {
          ((cg)this).Y = ((c)super).bI;
          ((cg)this).aa = ((c)super).bJ;
        } 
        ((cg)this).Z = ((fl)this).aT;
      } else {
        ((c)super).bM.d();
        if (!H && m != null && n != null)
          if (fl.aU > 0) {
            ((c)super).bM.a(((c)super).bJ);
          } else {
            ((c)super).bM.a(((c)super).bI);
            ((c)super).bM.a(((c)super).bJ);
          }  
      } 
      ((fl)this).aY = null;
      E.d();
      B = 0;
      C = -1;
      if (H) {
        n = null;
        m = null;
        H = false;
      } 
      if (m == null && n == null)
        ft.o.a(null, df.fn, fq.f, (byte)2, false, 0); 
      return;
    } 
    if (((c)super).bv == c) {
      str = this;
      fl.bi = 0;
      if (fl.aU > 0)
        bG = true; 
      if (!ft.A) {
        if (!H && s != null) {
          ((cg)this).Y = ((c)super).bI;
          ((c)super).bK.a = df.fx;
          if (o == null)
            ((c)super).bK.a = df.fv; 
          ((cg)this).aa = ((c)super).bK;
        } 
        ((cg)this).Z = ((fl)this).aT;
      } else {
        ((c)super).bM.d();
        if (!H && s != null) {
          ((c)super).bK.a = df.fx;
          if (o == null)
            ((c)super).bK.a = df.fv; 
          if (fl.aU > 0) {
            ((c)super).bM.a(((c)super).bK);
          } else {
            ((c)super).bM.a(((c)super).bI);
            ((c)super).bM.a(((c)super).bK);
          } 
        } 
      } 
      ((fl)this).aY = null;
      E.d();
      B = 0;
      C = 0;
      if (H) {
        o = null;
        H = false;
      } 
    } 
  }
  
  public final void c() {
    if (fl.aU == 0)
      bG = false; 
    fl.bi = 0;
    fl.aO = 0;
    E.d();
    super.c();
  }
  
  public final void a(bx parambx) {
    // Byte code:
    //   0: getstatic c.B : B
    //   3: ifne -> 45
    //   6: getstatic ft.A : Z
    //   9: ifne -> 45
    //   12: getstatic fl.aO : B
    //   15: iconst_1
    //   16: if_icmpne -> 45
    //   19: aload_1
    //   20: aload_0
    //   21: getfield V : I
    //   24: iconst_2
    //   25: iadd
    //   26: aload_0
    //   27: getfield W : I
    //   30: iconst_2
    //   31: iadd
    //   32: getstatic fl.S : I
    //   35: iconst_4
    //   36: isub
    //   37: getstatic fl.T : I
    //   40: iconst_4
    //   41: isub
    //   42: invokevirtual c : (IIII)V
    //   45: getstatic ft.B : Z
    //   48: ifeq -> 83
    //   51: aload_1
    //   52: aload_0
    //   53: getfield V : I
    //   56: iconst_4
    //   57: iadd
    //   58: aload_0
    //   59: getfield W : I
    //   62: iconst_4
    //   63: iadd
    //   64: getstatic fl.S : I
    //   67: bipush #8
    //   69: isub
    //   70: getstatic fl.T : I
    //   73: bipush #8
    //   75: isub
    //   76: iconst_4
    //   77: invokestatic c : (Lbx;IIIII)V
    //   80: goto -> 336
    //   83: aload_0
    //   84: aload_1
    //   85: astore_3
    //   86: astore_2
    //   87: iconst_0
    //   88: istore #4
    //   90: goto -> 327
    //   93: iconst_0
    //   94: istore #5
    //   96: goto -> 315
    //   99: aload_2
    //   100: bipush #12
    //   102: putfield bB : I
    //   105: iload #5
    //   107: ifne -> 116
    //   110: aload_2
    //   111: bipush #12
    //   113: putfield bB : I
    //   116: iload #4
    //   118: aload_2
    //   119: getfield bz : I
    //   122: if_icmpne -> 225
    //   125: iload #5
    //   127: aload_2
    //   128: getfield bA : I
    //   131: if_icmpne -> 182
    //   134: aload_3
    //   135: getstatic fl.aP : [Laq;
    //   138: aload_2
    //   139: getfield bB : I
    //   142: aaload
    //   143: aload_2
    //   144: getfield V : I
    //   147: iconst_4
    //   148: iadd
    //   149: getstatic fl.S : I
    //   152: bipush #8
    //   154: isub
    //   155: iadd
    //   156: bipush #32
    //   158: isub
    //   159: aload_2
    //   160: getfield W : I
    //   163: iconst_4
    //   164: iadd
    //   165: getstatic fl.T : I
    //   168: iadd
    //   169: bipush #8
    //   171: isub
    //   172: bipush #32
    //   174: isub
    //   175: iconst_0
    //   176: invokevirtual a : (Laq;III)V
    //   179: goto -> 312
    //   182: aload_3
    //   183: getstatic fl.aP : [Laq;
    //   186: aload_2
    //   187: getfield bB : I
    //   190: aaload
    //   191: aload_2
    //   192: getfield V : I
    //   195: iconst_4
    //   196: iadd
    //   197: getstatic fl.S : I
    //   200: bipush #8
    //   202: isub
    //   203: iadd
    //   204: bipush #32
    //   206: isub
    //   207: aload_2
    //   208: getfield W : I
    //   211: iconst_4
    //   212: iadd
    //   213: iload #5
    //   215: iconst_5
    //   216: ishl
    //   217: iadd
    //   218: iconst_0
    //   219: invokevirtual a : (Laq;III)V
    //   222: goto -> 312
    //   225: iload #5
    //   227: aload_2
    //   228: getfield bA : I
    //   231: if_icmpne -> 277
    //   234: aload_3
    //   235: getstatic fl.aP : [Laq;
    //   238: aload_2
    //   239: getfield bB : I
    //   242: aaload
    //   243: aload_2
    //   244: getfield V : I
    //   247: iconst_4
    //   248: iadd
    //   249: iload #4
    //   251: iconst_5
    //   252: ishl
    //   253: iadd
    //   254: aload_2
    //   255: getfield W : I
    //   258: iconst_4
    //   259: iadd
    //   260: getstatic fl.T : I
    //   263: iadd
    //   264: bipush #8
    //   266: isub
    //   267: bipush #32
    //   269: isub
    //   270: iconst_0
    //   271: invokevirtual a : (Laq;III)V
    //   274: goto -> 312
    //   277: aload_3
    //   278: getstatic fl.aP : [Laq;
    //   281: aload_2
    //   282: getfield bB : I
    //   285: aaload
    //   286: aload_2
    //   287: getfield V : I
    //   290: iconst_4
    //   291: iadd
    //   292: iload #4
    //   294: iconst_5
    //   295: ishl
    //   296: iadd
    //   297: aload_2
    //   298: getfield W : I
    //   301: iconst_4
    //   302: iadd
    //   303: iload #5
    //   305: iconst_5
    //   306: ishl
    //   307: iadd
    //   308: iconst_0
    //   309: invokevirtual a : (Laq;III)V
    //   312: iinc #5, 1
    //   315: iload #5
    //   317: aload_2
    //   318: getfield bA : I
    //   321: if_icmple -> 99
    //   324: iinc #4, 1
    //   327: iload #4
    //   329: aload_2
    //   330: getfield bz : I
    //   333: if_icmple -> 93
    //   336: aload_1
    //   337: aload_0
    //   338: getfield ba : Laq;
    //   341: aload_0
    //   342: getfield V : I
    //   345: getstatic fl.S : I
    //   348: iconst_2
    //   349: idiv
    //   350: iadd
    //   351: bipush #54
    //   353: isub
    //   354: aload_0
    //   355: getfield W : I
    //   358: getstatic fl.T : I
    //   361: iconst_2
    //   362: idiv
    //   363: iadd
    //   364: bipush #52
    //   366: isub
    //   367: iconst_0
    //   368: invokevirtual a : (Laq;III)V
    //   371: aload_1
    //   372: aload_0
    //   373: getfield ba : Laq;
    //   376: iconst_0
    //   377: iconst_0
    //   378: bipush #54
    //   380: bipush #105
    //   382: iconst_2
    //   383: aload_0
    //   384: getfield V : I
    //   387: getstatic fl.S : I
    //   390: iconst_2
    //   391: idiv
    //   392: iadd
    //   393: aload_0
    //   394: getfield W : I
    //   397: getstatic fl.T : I
    //   400: iconst_2
    //   401: idiv
    //   402: iadd
    //   403: bipush #52
    //   405: isub
    //   406: iconst_0
    //   407: invokevirtual a : (Laq;IIIIIIII)V
    //   410: aload_0
    //   411: getfield bv : B
    //   414: getstatic c.g : B
    //   417: if_icmpne -> 791
    //   420: aload_0
    //   421: aload_1
    //   422: astore_3
    //   423: astore_2
    //   424: iconst_0
    //   425: istore #4
    //   427: goto -> 676
    //   430: getstatic c.B : B
    //   433: ifeq -> 442
    //   436: iload #4
    //   438: iconst_5
    //   439: if_icmpne -> 673
    //   442: getstatic ft.B : Z
    //   445: ifeq -> 484
    //   448: aload_3
    //   449: aload_2
    //   450: getfield bD : [[I
    //   453: iload #4
    //   455: aaload
    //   456: iconst_0
    //   457: iaload
    //   458: bipush #10
    //   460: isub
    //   461: aload_2
    //   462: getfield bD : [[I
    //   465: iload #4
    //   467: aaload
    //   468: iconst_1
    //   469: iaload
    //   470: bipush #10
    //   472: isub
    //   473: bipush #20
    //   475: bipush #20
    //   477: iconst_2
    //   478: invokestatic c : (Lbx;IIIII)V
    //   481: goto -> 519
    //   484: aload_3
    //   485: getstatic fl.aP : [Laq;
    //   488: iconst_2
    //   489: aaload
    //   490: iconst_0
    //   491: iconst_0
    //   492: bipush #20
    //   494: bipush #20
    //   496: iconst_0
    //   497: aload_2
    //   498: getfield bD : [[I
    //   501: iload #4
    //   503: aaload
    //   504: iconst_0
    //   505: iaload
    //   506: aload_2
    //   507: getfield bD : [[I
    //   510: iload #4
    //   512: aaload
    //   513: iconst_1
    //   514: iaload
    //   515: iconst_3
    //   516: invokevirtual a : (Laq;IIIIIIII)V
    //   519: getstatic c.l : Lj;
    //   522: ifnull -> 647
    //   525: iload #4
    //   527: iconst_5
    //   528: if_icmpne -> 647
    //   531: getstatic c.B : B
    //   534: iconst_5
    //   535: if_icmpne -> 549
    //   538: aload_2
    //   539: getfield bQ : J
    //   542: ldc2_w 15
    //   545: lcmp
    //   546: ifle -> 647
    //   549: getstatic c.l : Lj;
    //   552: getfield u : I
    //   555: bipush #7
    //   557: if_icmpne -> 618
    //   560: getstatic c.l : Lj;
    //   563: getfield O : I
    //   566: invokestatic b : (I)Lj;
    //   569: dup
    //   570: astore #5
    //   572: ifnull -> 606
    //   575: aload #5
    //   577: aload_3
    //   578: aload_2
    //   579: getfield bD : [[I
    //   582: iload #4
    //   584: aaload
    //   585: iconst_0
    //   586: iaload
    //   587: aload_2
    //   588: getfield bD : [[I
    //   591: iload #4
    //   593: aaload
    //   594: iconst_1
    //   595: iaload
    //   596: bipush #21
    //   598: iconst_1
    //   599: iconst_0
    //   600: invokevirtual a : (Lbx;IIIII)V
    //   603: goto -> 647
    //   606: getstatic c.l : Lj;
    //   609: getfield O : I
    //   612: invokestatic c : (I)V
    //   615: goto -> 647
    //   618: getstatic c.l : Lj;
    //   621: aload_3
    //   622: aload_2
    //   623: getfield bD : [[I
    //   626: iload #4
    //   628: aaload
    //   629: iconst_0
    //   630: iaload
    //   631: aload_2
    //   632: getfield bD : [[I
    //   635: iload #4
    //   637: aaload
    //   638: iconst_1
    //   639: iaload
    //   640: bipush #21
    //   642: iconst_1
    //   643: iconst_0
    //   644: invokevirtual a : (Lbx;IIIII)V
    //   647: aload_3
    //   648: getstatic cg.ap : Laq;
    //   651: aload_2
    //   652: getfield bD : [[I
    //   655: iload #4
    //   657: aaload
    //   658: iconst_0
    //   659: iaload
    //   660: aload_2
    //   661: getfield bD : [[I
    //   664: iload #4
    //   666: aaload
    //   667: iconst_1
    //   668: iaload
    //   669: iconst_3
    //   670: invokevirtual a : (Laq;III)V
    //   673: iinc #4, 1
    //   676: iload #4
    //   678: aload_2
    //   679: getfield bD : [[I
    //   682: arraylength
    //   683: if_icmplt -> 430
    //   686: iconst_0
    //   687: istore #4
    //   689: goto -> 777
    //   692: getstatic c.G : Les;
    //   695: iload #4
    //   697: invokevirtual a : (I)Ljava/lang/Object;
    //   700: checkcast j
    //   703: dup
    //   704: astore #5
    //   706: ifnull -> 774
    //   709: aload #5
    //   711: getfield O : I
    //   714: invokestatic b : (I)Lj;
    //   717: dup
    //   718: astore #6
    //   720: ifnull -> 754
    //   723: aload #6
    //   725: aload_3
    //   726: aload_2
    //   727: getfield bD : [[I
    //   730: iload #4
    //   732: aaload
    //   733: iconst_0
    //   734: iaload
    //   735: aload_2
    //   736: getfield bD : [[I
    //   739: iload #4
    //   741: aaload
    //   742: iconst_1
    //   743: iaload
    //   744: bipush #21
    //   746: iconst_0
    //   747: iconst_0
    //   748: invokevirtual c : (Lbx;IIIII)V
    //   751: goto -> 762
    //   754: aload #5
    //   756: getfield O : I
    //   759: invokestatic c : (I)V
    //   762: getstatic c.h : [Ljava/lang/String;
    //   765: iload #4
    //   767: aaload
    //   768: ldc ''
    //   770: invokevirtual equals : (Ljava/lang/Object;)Z
    //   773: pop
    //   774: iinc #4, 1
    //   777: iload #4
    //   779: getstatic c.G : Les;
    //   782: invokevirtual c : ()I
    //   785: if_icmplt -> 692
    //   788: goto -> 2326
    //   791: aload_0
    //   792: getfield bv : B
    //   795: getstatic c.f : B
    //   798: if_icmpne -> 1066
    //   801: aload_0
    //   802: aload_1
    //   803: astore_3
    //   804: astore_2
    //   805: iconst_0
    //   806: istore #4
    //   808: goto -> 988
    //   811: getstatic c.B : B
    //   814: ifeq -> 823
    //   817: iload #4
    //   819: iconst_5
    //   820: if_icmpne -> 985
    //   823: getstatic ft.B : Z
    //   826: ifeq -> 865
    //   829: aload_3
    //   830: aload_2
    //   831: getfield bD : [[I
    //   834: iload #4
    //   836: aaload
    //   837: iconst_0
    //   838: iaload
    //   839: bipush #10
    //   841: isub
    //   842: aload_2
    //   843: getfield bD : [[I
    //   846: iload #4
    //   848: aaload
    //   849: iconst_1
    //   850: iaload
    //   851: bipush #10
    //   853: isub
    //   854: bipush #20
    //   856: bipush #20
    //   858: iconst_2
    //   859: invokestatic c : (Lbx;IIIII)V
    //   862: goto -> 900
    //   865: aload_3
    //   866: getstatic fl.aP : [Laq;
    //   869: iconst_2
    //   870: aaload
    //   871: iconst_0
    //   872: iconst_0
    //   873: bipush #20
    //   875: bipush #20
    //   877: iconst_0
    //   878: aload_2
    //   879: getfield bD : [[I
    //   882: iload #4
    //   884: aaload
    //   885: iconst_0
    //   886: iaload
    //   887: aload_2
    //   888: getfield bD : [[I
    //   891: iload #4
    //   893: aaload
    //   894: iconst_1
    //   895: iaload
    //   896: iconst_3
    //   897: invokevirtual a : (Laq;IIIIIIII)V
    //   900: getstatic c.l : Lj;
    //   903: ifnull -> 959
    //   906: iload #4
    //   908: iconst_5
    //   909: if_icmpne -> 959
    //   912: getstatic c.B : B
    //   915: iconst_5
    //   916: if_icmpne -> 930
    //   919: aload_2
    //   920: getfield bQ : J
    //   923: ldc2_w 15
    //   926: lcmp
    //   927: ifle -> 959
    //   930: getstatic c.l : Lj;
    //   933: aload_3
    //   934: aload_2
    //   935: getfield bD : [[I
    //   938: iload #4
    //   940: aaload
    //   941: iconst_0
    //   942: iaload
    //   943: aload_2
    //   944: getfield bD : [[I
    //   947: iload #4
    //   949: aaload
    //   950: iconst_1
    //   951: iaload
    //   952: bipush #21
    //   954: iconst_1
    //   955: iconst_0
    //   956: invokevirtual a : (Lbx;IIIII)V
    //   959: aload_3
    //   960: getstatic cg.ap : Laq;
    //   963: aload_2
    //   964: getfield bD : [[I
    //   967: iload #4
    //   969: aaload
    //   970: iconst_0
    //   971: iaload
    //   972: aload_2
    //   973: getfield bD : [[I
    //   976: iload #4
    //   978: aaload
    //   979: iconst_1
    //   980: iaload
    //   981: iconst_3
    //   982: invokevirtual a : (Laq;III)V
    //   985: iinc #4, 1
    //   988: iload #4
    //   990: aload_2
    //   991: getfield bD : [[I
    //   994: arraylength
    //   995: if_icmplt -> 811
    //   998: iconst_0
    //   999: istore #4
    //   1001: goto -> 1052
    //   1004: getstatic c.G : Les;
    //   1007: iload #4
    //   1009: invokevirtual a : (I)Ljava/lang/Object;
    //   1012: checkcast j
    //   1015: dup
    //   1016: astore #5
    //   1018: ifnull -> 1049
    //   1021: aload #5
    //   1023: aload_3
    //   1024: aload_2
    //   1025: getfield bD : [[I
    //   1028: iload #4
    //   1030: aaload
    //   1031: iconst_0
    //   1032: iaload
    //   1033: aload_2
    //   1034: getfield bD : [[I
    //   1037: iload #4
    //   1039: aaload
    //   1040: iconst_1
    //   1041: iaload
    //   1042: bipush #21
    //   1044: iconst_0
    //   1045: iconst_0
    //   1046: invokevirtual c : (Lbx;IIIII)V
    //   1049: iinc #4, 1
    //   1052: iload #4
    //   1054: getstatic c.G : Les;
    //   1057: invokevirtual c : ()I
    //   1060: if_icmplt -> 1004
    //   1063: goto -> 2326
    //   1066: aload_0
    //   1067: getfield bv : B
    //   1070: getstatic c.e : B
    //   1073: if_icmpne -> 1367
    //   1076: aload_0
    //   1077: aload_1
    //   1078: astore_3
    //   1079: astore_2
    //   1080: iconst_0
    //   1081: istore #4
    //   1083: goto -> 1289
    //   1086: getstatic c.B : B
    //   1089: ifeq -> 1098
    //   1092: iload #4
    //   1094: iconst_5
    //   1095: if_icmpne -> 1286
    //   1098: getstatic ft.B : Z
    //   1101: ifeq -> 1140
    //   1104: aload_3
    //   1105: aload_2
    //   1106: getfield bD : [[I
    //   1109: iload #4
    //   1111: aaload
    //   1112: iconst_0
    //   1113: iaload
    //   1114: bipush #10
    //   1116: isub
    //   1117: aload_2
    //   1118: getfield bD : [[I
    //   1121: iload #4
    //   1123: aaload
    //   1124: iconst_1
    //   1125: iaload
    //   1126: bipush #10
    //   1128: isub
    //   1129: bipush #20
    //   1131: bipush #20
    //   1133: iconst_2
    //   1134: invokestatic c : (Lbx;IIIII)V
    //   1137: goto -> 1175
    //   1140: aload_3
    //   1141: getstatic fl.aP : [Laq;
    //   1144: iconst_2
    //   1145: aaload
    //   1146: iconst_0
    //   1147: iconst_0
    //   1148: bipush #20
    //   1150: bipush #20
    //   1152: iconst_0
    //   1153: aload_2
    //   1154: getfield bD : [[I
    //   1157: iload #4
    //   1159: aaload
    //   1160: iconst_0
    //   1161: iaload
    //   1162: aload_2
    //   1163: getfield bD : [[I
    //   1166: iload #4
    //   1168: aaload
    //   1169: iconst_1
    //   1170: iaload
    //   1171: iconst_3
    //   1172: invokevirtual a : (Laq;IIIIIIII)V
    //   1175: getstatic c.l : Lj;
    //   1178: ifnull -> 1260
    //   1181: iload #4
    //   1183: iconst_5
    //   1184: if_icmpne -> 1260
    //   1187: getstatic c.B : B
    //   1190: iconst_5
    //   1191: if_icmpne -> 1205
    //   1194: aload_2
    //   1195: getfield bQ : J
    //   1198: ldc2_w 15
    //   1201: lcmp
    //   1202: ifle -> 1260
    //   1205: getstatic c.l : Lj;
    //   1208: getfield O : I
    //   1211: invokestatic b : (I)Lj;
    //   1214: dup
    //   1215: astore #5
    //   1217: ifnull -> 1251
    //   1220: aload #5
    //   1222: aload_3
    //   1223: aload_2
    //   1224: getfield bD : [[I
    //   1227: iload #4
    //   1229: aaload
    //   1230: iconst_0
    //   1231: iaload
    //   1232: aload_2
    //   1233: getfield bD : [[I
    //   1236: iload #4
    //   1238: aaload
    //   1239: iconst_1
    //   1240: iaload
    //   1241: bipush #21
    //   1243: iconst_1
    //   1244: iconst_0
    //   1245: invokevirtual a : (Lbx;IIIII)V
    //   1248: goto -> 1260
    //   1251: getstatic c.l : Lj;
    //   1254: getfield O : I
    //   1257: invokestatic c : (I)V
    //   1260: aload_3
    //   1261: getstatic cg.ap : Laq;
    //   1264: aload_2
    //   1265: getfield bD : [[I
    //   1268: iload #4
    //   1270: aaload
    //   1271: iconst_0
    //   1272: iaload
    //   1273: aload_2
    //   1274: getfield bD : [[I
    //   1277: iload #4
    //   1279: aaload
    //   1280: iconst_1
    //   1281: iaload
    //   1282: iconst_3
    //   1283: invokevirtual a : (Laq;III)V
    //   1286: iinc #4, 1
    //   1289: iload #4
    //   1291: aload_2
    //   1292: getfield bD : [[I
    //   1295: arraylength
    //   1296: if_icmplt -> 1086
    //   1299: iconst_0
    //   1300: istore #4
    //   1302: goto -> 1353
    //   1305: getstatic c.G : Les;
    //   1308: iload #4
    //   1310: invokevirtual a : (I)Ljava/lang/Object;
    //   1313: checkcast j
    //   1316: dup
    //   1317: astore #5
    //   1319: ifnull -> 1350
    //   1322: aload #5
    //   1324: aload_3
    //   1325: aload_2
    //   1326: getfield bD : [[I
    //   1329: iload #4
    //   1331: aaload
    //   1332: iconst_0
    //   1333: iaload
    //   1334: aload_2
    //   1335: getfield bD : [[I
    //   1338: iload #4
    //   1340: aaload
    //   1341: iconst_1
    //   1342: iaload
    //   1343: bipush #21
    //   1345: iconst_0
    //   1346: iconst_0
    //   1347: invokevirtual c : (Lbx;IIIII)V
    //   1350: iinc #4, 1
    //   1353: iload #4
    //   1355: getstatic c.G : Les;
    //   1358: invokevirtual c : ()I
    //   1361: if_icmplt -> 1305
    //   1364: goto -> 2326
    //   1367: aload_0
    //   1368: getfield bv : B
    //   1371: getstatic c.d : B
    //   1374: if_icmpne -> 1642
    //   1377: aload_0
    //   1378: aload_1
    //   1379: astore_3
    //   1380: astore_2
    //   1381: iconst_0
    //   1382: istore #4
    //   1384: goto -> 1564
    //   1387: getstatic c.B : B
    //   1390: ifeq -> 1399
    //   1393: iload #4
    //   1395: iconst_5
    //   1396: if_icmpne -> 1561
    //   1399: getstatic ft.B : Z
    //   1402: ifeq -> 1441
    //   1405: aload_3
    //   1406: aload_2
    //   1407: getfield bD : [[I
    //   1410: iload #4
    //   1412: aaload
    //   1413: iconst_0
    //   1414: iaload
    //   1415: bipush #10
    //   1417: isub
    //   1418: aload_2
    //   1419: getfield bD : [[I
    //   1422: iload #4
    //   1424: aaload
    //   1425: iconst_1
    //   1426: iaload
    //   1427: bipush #10
    //   1429: isub
    //   1430: bipush #20
    //   1432: bipush #20
    //   1434: iconst_2
    //   1435: invokestatic c : (Lbx;IIIII)V
    //   1438: goto -> 1476
    //   1441: aload_3
    //   1442: getstatic fl.aP : [Laq;
    //   1445: iconst_2
    //   1446: aaload
    //   1447: iconst_0
    //   1448: iconst_0
    //   1449: bipush #20
    //   1451: bipush #20
    //   1453: iconst_0
    //   1454: aload_2
    //   1455: getfield bD : [[I
    //   1458: iload #4
    //   1460: aaload
    //   1461: iconst_0
    //   1462: iaload
    //   1463: aload_2
    //   1464: getfield bD : [[I
    //   1467: iload #4
    //   1469: aaload
    //   1470: iconst_1
    //   1471: iaload
    //   1472: iconst_3
    //   1473: invokevirtual a : (Laq;IIIIIIII)V
    //   1476: getstatic c.l : Lj;
    //   1479: ifnull -> 1535
    //   1482: iload #4
    //   1484: iconst_5
    //   1485: if_icmpne -> 1535
    //   1488: getstatic c.B : B
    //   1491: iconst_5
    //   1492: if_icmpne -> 1506
    //   1495: aload_2
    //   1496: getfield bQ : J
    //   1499: ldc2_w 15
    //   1502: lcmp
    //   1503: ifle -> 1535
    //   1506: getstatic c.l : Lj;
    //   1509: aload_3
    //   1510: aload_2
    //   1511: getfield bD : [[I
    //   1514: iload #4
    //   1516: aaload
    //   1517: iconst_0
    //   1518: iaload
    //   1519: aload_2
    //   1520: getfield bD : [[I
    //   1523: iload #4
    //   1525: aaload
    //   1526: iconst_1
    //   1527: iaload
    //   1528: bipush #21
    //   1530: iconst_1
    //   1531: iconst_0
    //   1532: invokevirtual a : (Lbx;IIIII)V
    //   1535: aload_3
    //   1536: getstatic cg.ap : Laq;
    //   1539: aload_2
    //   1540: getfield bD : [[I
    //   1543: iload #4
    //   1545: aaload
    //   1546: iconst_0
    //   1547: iaload
    //   1548: aload_2
    //   1549: getfield bD : [[I
    //   1552: iload #4
    //   1554: aaload
    //   1555: iconst_1
    //   1556: iaload
    //   1557: iconst_3
    //   1558: invokevirtual a : (Laq;III)V
    //   1561: iinc #4, 1
    //   1564: iload #4
    //   1566: aload_2
    //   1567: getfield bD : [[I
    //   1570: arraylength
    //   1571: if_icmplt -> 1387
    //   1574: iconst_0
    //   1575: istore #4
    //   1577: goto -> 1628
    //   1580: getstatic c.G : Les;
    //   1583: iload #4
    //   1585: invokevirtual a : (I)Ljava/lang/Object;
    //   1588: checkcast j
    //   1591: dup
    //   1592: astore #5
    //   1594: ifnull -> 1625
    //   1597: aload #5
    //   1599: aload_3
    //   1600: aload_2
    //   1601: getfield bD : [[I
    //   1604: iload #4
    //   1606: aaload
    //   1607: iconst_0
    //   1608: iaload
    //   1609: aload_2
    //   1610: getfield bD : [[I
    //   1613: iload #4
    //   1615: aaload
    //   1616: iconst_1
    //   1617: iaload
    //   1618: bipush #21
    //   1620: iconst_0
    //   1621: iconst_0
    //   1622: invokevirtual c : (Lbx;IIIII)V
    //   1625: iinc #4, 1
    //   1628: iload #4
    //   1630: getstatic c.G : Les;
    //   1633: invokevirtual c : ()I
    //   1636: if_icmplt -> 1580
    //   1639: goto -> 2326
    //   1642: aload_0
    //   1643: getfield bv : B
    //   1646: ifne -> 2293
    //   1649: aload_0
    //   1650: aload_1
    //   1651: astore_3
    //   1652: astore_2
    //   1653: iconst_0
    //   1654: istore #4
    //   1656: goto -> 2280
    //   1659: getstatic c.B : B
    //   1662: ifeq -> 1671
    //   1665: iload #4
    //   1667: iconst_5
    //   1668: if_icmpne -> 2277
    //   1671: getstatic ft.B : Z
    //   1674: ifeq -> 1713
    //   1677: aload_3
    //   1678: aload_2
    //   1679: getfield bD : [[I
    //   1682: iload #4
    //   1684: aaload
    //   1685: iconst_0
    //   1686: iaload
    //   1687: bipush #10
    //   1689: isub
    //   1690: aload_2
    //   1691: getfield bD : [[I
    //   1694: iload #4
    //   1696: aaload
    //   1697: iconst_1
    //   1698: iaload
    //   1699: bipush #10
    //   1701: isub
    //   1702: bipush #20
    //   1704: bipush #20
    //   1706: iconst_2
    //   1707: invokestatic c : (Lbx;IIIII)V
    //   1710: goto -> 1748
    //   1713: aload_3
    //   1714: getstatic fl.aP : [Laq;
    //   1717: iconst_2
    //   1718: aaload
    //   1719: iconst_0
    //   1720: iconst_0
    //   1721: bipush #20
    //   1723: bipush #20
    //   1725: iconst_0
    //   1726: aload_2
    //   1727: getfield bD : [[I
    //   1730: iload #4
    //   1732: aaload
    //   1733: iconst_0
    //   1734: iaload
    //   1735: aload_2
    //   1736: getfield bD : [[I
    //   1739: iload #4
    //   1741: aaload
    //   1742: iconst_1
    //   1743: iaload
    //   1744: iconst_3
    //   1745: invokevirtual a : (Laq;IIIIIIII)V
    //   1748: getstatic c.l : Lj;
    //   1751: ifnull -> 2139
    //   1754: aload_2
    //   1755: getfield bb : Z
    //   1758: ifeq -> 1872
    //   1761: iload #4
    //   1763: iconst_5
    //   1764: if_icmpge -> 1799
    //   1767: getstatic c.l : Lj;
    //   1770: aload_3
    //   1771: aload_2
    //   1772: getfield bD : [[I
    //   1775: iload #4
    //   1777: aaload
    //   1778: iconst_0
    //   1779: iaload
    //   1780: aload_2
    //   1781: getfield bD : [[I
    //   1784: iload #4
    //   1786: aaload
    //   1787: iconst_1
    //   1788: iaload
    //   1789: bipush #21
    //   1791: iconst_1
    //   1792: iconst_0
    //   1793: invokevirtual a : (Lbx;IIIII)V
    //   1796: goto -> 2139
    //   1799: getstatic c.l : Lj;
    //   1802: getfield ak : Lbw;
    //   1805: ifnull -> 2139
    //   1808: getstatic c.l : Lj;
    //   1811: getfield ak : Lbw;
    //   1814: getfield O : I
    //   1817: invokestatic b : (I)Lj;
    //   1820: dup
    //   1821: astore #5
    //   1823: ifnull -> 1857
    //   1826: aload #5
    //   1828: aload_3
    //   1829: aload_2
    //   1830: getfield bD : [[I
    //   1833: iload #4
    //   1835: aaload
    //   1836: iconst_0
    //   1837: iaload
    //   1838: aload_2
    //   1839: getfield bD : [[I
    //   1842: iload #4
    //   1844: aaload
    //   1845: iconst_1
    //   1846: iaload
    //   1847: bipush #21
    //   1849: iconst_1
    //   1850: iconst_0
    //   1851: invokevirtual a : (Lbx;IIIII)V
    //   1854: goto -> 2139
    //   1857: getstatic c.l : Lj;
    //   1860: getfield ak : Lbw;
    //   1863: getfield O : I
    //   1866: invokestatic c : (I)V
    //   1869: goto -> 2139
    //   1872: iload #4
    //   1874: iconst_5
    //   1875: if_icmpge -> 2029
    //   1878: getstatic c.q : [S
    //   1881: iload #4
    //   1883: saload
    //   1884: invokestatic b : (I)Lj;
    //   1887: dup
    //   1888: astore #5
    //   1890: ifnull -> 2017
    //   1893: aload #5
    //   1895: getfield A : B
    //   1898: bipush #11
    //   1900: if_icmpne -> 1909
    //   1903: getstatic c.D : Z
    //   1906: ifne -> 1934
    //   1909: iload #4
    //   1911: iconst_4
    //   1912: if_icmpge -> 2139
    //   1915: getstatic c.k : [Lb;
    //   1918: getstatic c.l : Lj;
    //   1921: getfield z : B
    //   1924: aaload
    //   1925: getfield e : [B
    //   1928: iload #4
    //   1930: baload
    //   1931: ifle -> 2139
    //   1934: aload #5
    //   1936: getfield A : B
    //   1939: bipush #11
    //   1941: if_icmpne -> 1987
    //   1944: getstatic c.D : Z
    //   1947: ifeq -> 1987
    //   1950: getstatic c.I : Lbw;
    //   1953: ifnull -> 1987
    //   1956: getstatic c.I : Lbw;
    //   1959: aload_3
    //   1960: aload_2
    //   1961: getfield bD : [[I
    //   1964: iload #4
    //   1966: aaload
    //   1967: iconst_0
    //   1968: iaload
    //   1969: aload_2
    //   1970: getfield bD : [[I
    //   1973: iload #4
    //   1975: aaload
    //   1976: iconst_1
    //   1977: iaload
    //   1978: bipush #21
    //   1980: iconst_0
    //   1981: invokevirtual a : (Lbx;IIII)V
    //   1984: goto -> 2139
    //   1987: aload #5
    //   1989: aload_3
    //   1990: aload_2
    //   1991: getfield bD : [[I
    //   1994: iload #4
    //   1996: aaload
    //   1997: iconst_0
    //   1998: iaload
    //   1999: aload_2
    //   2000: getfield bD : [[I
    //   2003: iload #4
    //   2005: aaload
    //   2006: iconst_1
    //   2007: iaload
    //   2008: bipush #21
    //   2010: iconst_0
    //   2011: invokevirtual a : (Lbx;IIII)V
    //   2014: goto -> 2139
    //   2017: getstatic c.q : [S
    //   2020: iload #4
    //   2022: saload
    //   2023: invokestatic c : (I)V
    //   2026: goto -> 2139
    //   2029: iload #4
    //   2031: iconst_5
    //   2032: if_icmpne -> 2139
    //   2035: getstatic c.B : B
    //   2038: iconst_5
    //   2039: if_icmpne -> 2053
    //   2042: aload_2
    //   2043: getfield bQ : J
    //   2046: ldc2_w 15
    //   2049: lcmp
    //   2050: ifle -> 2082
    //   2053: getstatic c.l : Lj;
    //   2056: aload_3
    //   2057: aload_2
    //   2058: getfield bD : [[I
    //   2061: iload #4
    //   2063: aaload
    //   2064: iconst_0
    //   2065: iaload
    //   2066: aload_2
    //   2067: getfield bD : [[I
    //   2070: iload #4
    //   2072: aaload
    //   2073: iconst_1
    //   2074: iaload
    //   2075: bipush #21
    //   2077: iconst_1
    //   2078: iconst_0
    //   2079: invokevirtual a : (Lbx;IIIII)V
    //   2082: getstatic c.B : B
    //   2085: ifne -> 2139
    //   2088: getstatic o.j : Lo;
    //   2091: aload_3
    //   2092: new java/lang/StringBuffer
    //   2095: dup
    //   2096: ldc 'Lv '
    //   2098: invokespecial <init> : (Ljava/lang/String;)V
    //   2101: getstatic c.l : Lj;
    //   2104: getfield z : B
    //   2107: invokevirtual append : (I)Ljava/lang/StringBuffer;
    //   2110: invokevirtual toString : ()Ljava/lang/String;
    //   2113: aload_2
    //   2114: getfield bD : [[I
    //   2117: iload #4
    //   2119: aaload
    //   2120: iconst_0
    //   2121: iaload
    //   2122: aload_2
    //   2123: getfield bD : [[I
    //   2126: iload #4
    //   2128: aaload
    //   2129: iconst_1
    //   2130: iaload
    //   2131: bipush #22
    //   2133: isub
    //   2134: iconst_2
    //   2135: iconst_0
    //   2136: invokevirtual a : (Lbx;Ljava/lang/String;IIIZ)V
    //   2139: aload_3
    //   2140: getstatic cg.ap : Laq;
    //   2143: aload_2
    //   2144: getfield bD : [[I
    //   2147: iload #4
    //   2149: aaload
    //   2150: iconst_0
    //   2151: iaload
    //   2152: aload_2
    //   2153: getfield bD : [[I
    //   2156: iload #4
    //   2158: aaload
    //   2159: iconst_1
    //   2160: iaload
    //   2161: iconst_3
    //   2162: invokevirtual a : (Laq;III)V
    //   2165: getstatic c.l : Lj;
    //   2168: ifnull -> 2277
    //   2171: iload #4
    //   2173: iconst_4
    //   2174: if_icmpge -> 2231
    //   2177: getstatic c.k : [Lb;
    //   2180: getstatic c.l : Lj;
    //   2183: getfield z : B
    //   2186: aaload
    //   2187: getfield e : [B
    //   2190: iload #4
    //   2192: baload
    //   2193: getstatic c.p : [I
    //   2196: iload #4
    //   2198: iaload
    //   2199: if_icmple -> 2231
    //   2202: aload_3
    //   2203: getstatic cg.aq : Laq;
    //   2206: aload_2
    //   2207: getfield bD : [[I
    //   2210: iload #4
    //   2212: aaload
    //   2213: iconst_0
    //   2214: iaload
    //   2215: aload_2
    //   2216: getfield bD : [[I
    //   2219: iload #4
    //   2221: aaload
    //   2222: iconst_1
    //   2223: iaload
    //   2224: iconst_3
    //   2225: invokevirtual a : (Laq;III)V
    //   2228: goto -> 2277
    //   2231: iload #4
    //   2233: iconst_5
    //   2234: if_icmpne -> 2277
    //   2237: getstatic c.B : B
    //   2240: iconst_5
    //   2241: if_icmpne -> 2277
    //   2244: getstatic c.C : B
    //   2247: iconst_4
    //   2248: if_icmpne -> 2277
    //   2251: aload_3
    //   2252: getstatic cg.aq : Laq;
    //   2255: aload_2
    //   2256: getfield bD : [[I
    //   2259: iload #4
    //   2261: aaload
    //   2262: iconst_0
    //   2263: iaload
    //   2264: aload_2
    //   2265: getfield bD : [[I
    //   2268: iload #4
    //   2270: aaload
    //   2271: iconst_1
    //   2272: iaload
    //   2273: iconst_3
    //   2274: invokevirtual a : (Laq;III)V
    //   2277: iinc #4, 1
    //   2280: iload #4
    //   2282: aload_2
    //   2283: getfield bD : [[I
    //   2286: arraylength
    //   2287: if_icmplt -> 1659
    //   2290: goto -> 2326
    //   2293: aload_0
    //   2294: getfield bv : B
    //   2297: getstatic c.b : B
    //   2300: if_icmpne -> 2311
    //   2303: aload_0
    //   2304: aload_1
    //   2305: invokespecial e : (Lbx;)V
    //   2308: goto -> 2326
    //   2311: aload_0
    //   2312: getfield bv : B
    //   2315: getstatic c.c : B
    //   2318: if_icmpne -> 2326
    //   2321: aload_0
    //   2322: aload_1
    //   2323: invokespecial b : (Lbx;)V
    //   2326: iconst_0
    //   2327: istore_2
    //   2328: goto -> 2350
    //   2331: getstatic c.E : Les;
    //   2334: iload_2
    //   2335: invokevirtual a : (I)Ljava/lang/Object;
    //   2338: checkcast dx
    //   2341: dup
    //   2342: astore_3
    //   2343: aload_1
    //   2344: invokevirtual a : (Lbx;)V
    //   2347: iinc #2, 1
    //   2350: iload_2
    //   2351: getstatic c.E : Les;
    //   2354: invokevirtual c : ()I
    //   2357: if_icmplt -> 2331
    //   2360: getstatic c.bG : Z
    //   2363: ifne -> 2372
    //   2366: getstatic fl.aU : I
    //   2369: ifle -> 3024
    //   2372: aload_0
    //   2373: aload_1
    //   2374: aload_0
    //   2375: getfield bE : I
    //   2378: aload_0
    //   2379: getfield bF : I
    //   2382: istore #5
    //   2384: istore #4
    //   2386: astore_3
    //   2387: dup
    //   2388: astore_2
    //   2389: getfield bv : B
    //   2392: getstatic c.g : B
    //   2395: if_icmpne -> 2545
    //   2398: aload_2
    //   2399: aload_3
    //   2400: iload #4
    //   2402: iload #5
    //   2404: istore #9
    //   2406: istore #8
    //   2408: astore #7
    //   2410: astore #6
    //   2412: getstatic c.l : Lj;
    //   2415: ifnull -> 2504
    //   2418: getstatic fl.aU : I
    //   2421: ifle -> 2472
    //   2424: getstatic c.l : Lj;
    //   2427: getfield g : Ljava/lang/String;
    //   2430: ifnull -> 2472
    //   2433: aload #7
    //   2435: iload #8
    //   2437: getstatic fl.aU : I
    //   2440: iconst_2
    //   2441: idiv
    //   2442: iadd
    //   2443: iload #9
    //   2445: getstatic fl.aM : B
    //   2448: iconst_4
    //   2449: idiv
    //   2450: isub
    //   2451: getstatic fl.aU : I
    //   2454: getstatic c.l : Lj;
    //   2457: getfield g : Ljava/lang/String;
    //   2460: getstatic c.l : Lj;
    //   2463: getfield N : I
    //   2466: invokestatic a : (Lbx;IIILjava/lang/String;I)V
    //   2469: goto -> 2504
    //   2472: getstatic c.l : Lj;
    //   2475: getfield g : Ljava/lang/String;
    //   2478: ifnull -> 2504
    //   2481: aload #7
    //   2483: iload #8
    //   2485: iload #9
    //   2487: aload #6
    //   2489: getfield bC : I
    //   2492: sipush #150
    //   2495: getstatic c.l : Lj;
    //   2498: getfield g : Ljava/lang/String;
    //   2501: invokestatic a : (Lbx;IIIILjava/lang/String;)V
    //   2504: getstatic c.l : Lj;
    //   2507: ifnonnull -> 2517
    //   2510: aload_2
    //   2511: getfield bd : Z
    //   2514: ifne -> 2530
    //   2517: getstatic c.l : Lj;
    //   2520: ifnull -> 3024
    //   2523: aload_2
    //   2524: getfield be : Z
    //   2527: ifeq -> 3024
    //   2530: aload_2
    //   2531: aload_3
    //   2532: iload #4
    //   2534: iload #5
    //   2536: bipush #10
    //   2538: isub
    //   2539: invokespecial b : (Lbx;II)V
    //   2542: goto -> 3024
    //   2545: aload_2
    //   2546: getfield bv : B
    //   2549: getstatic c.e : B
    //   2552: if_icmpne -> 2664
    //   2555: aload_2
    //   2556: aload_3
    //   2557: iload #4
    //   2559: iload #5
    //   2561: istore #9
    //   2563: istore #8
    //   2565: astore #7
    //   2567: astore #6
    //   2569: getstatic c.l : Lj;
    //   2572: ifnull -> 2661
    //   2575: getstatic fl.aU : I
    //   2578: ifle -> 2629
    //   2581: getstatic c.l : Lj;
    //   2584: getfield g : Ljava/lang/String;
    //   2587: ifnull -> 2629
    //   2590: aload #7
    //   2592: iload #8
    //   2594: getstatic fl.aU : I
    //   2597: iconst_2
    //   2598: idiv
    //   2599: iadd
    //   2600: iload #9
    //   2602: getstatic fl.aM : B
    //   2605: iconst_4
    //   2606: idiv
    //   2607: isub
    //   2608: getstatic fl.aU : I
    //   2611: getstatic c.l : Lj;
    //   2614: getfield g : Ljava/lang/String;
    //   2617: getstatic c.l : Lj;
    //   2620: getfield N : I
    //   2623: invokestatic a : (Lbx;IIILjava/lang/String;I)V
    //   2626: goto -> 3024
    //   2629: getstatic c.l : Lj;
    //   2632: getfield g : Ljava/lang/String;
    //   2635: ifnull -> 2661
    //   2638: aload #7
    //   2640: iload #8
    //   2642: iload #9
    //   2644: aload #6
    //   2646: getfield bC : I
    //   2649: sipush #150
    //   2652: getstatic c.l : Lj;
    //   2655: getfield g : Ljava/lang/String;
    //   2658: invokestatic a : (Lbx;IIIILjava/lang/String;)V
    //   2661: goto -> 3024
    //   2664: aload_2
    //   2665: getfield bv : B
    //   2668: getstatic c.d : B
    //   2671: if_icmpeq -> 2684
    //   2674: aload_2
    //   2675: getfield bv : B
    //   2678: getstatic c.f : B
    //   2681: if_icmpne -> 2707
    //   2684: aload_2
    //   2685: aload_3
    //   2686: astore #7
    //   2688: astore #6
    //   2690: getstatic c.l : Lj;
    //   2693: ifnull -> 2704
    //   2696: aload #6
    //   2698: aload #7
    //   2700: iconst_0
    //   2701: invokevirtual c : (Lbx;Z)V
    //   2704: goto -> 3024
    //   2707: aload_2
    //   2708: getfield bv : B
    //   2711: ifne -> 2726
    //   2714: aload_2
    //   2715: aload_3
    //   2716: iload #4
    //   2718: iload #5
    //   2720: invokespecial c : (Lbx;II)V
    //   2723: goto -> 3024
    //   2726: aload_2
    //   2727: getfield bv : B
    //   2730: getstatic c.b : B
    //   2733: if_icmpne -> 3005
    //   2736: getstatic c.H : Z
    //   2739: ifne -> 3024
    //   2742: aload_2
    //   2743: aload_3
    //   2744: iload #4
    //   2746: iload #5
    //   2748: istore #9
    //   2750: istore #8
    //   2752: astore #7
    //   2754: astore #6
    //   2756: getstatic c.m : Lj;
    //   2759: ifnull -> 2768
    //   2762: getstatic c.n : Lj;
    //   2765: ifnonnull -> 2771
    //   2768: goto -> 3024
    //   2771: getstatic ft.ab : I
    //   2774: istore_2
    //   2775: getstatic fl.aU : I
    //   2778: ifle -> 2834
    //   2781: getstatic o.f : Lo;
    //   2784: aload #7
    //   2786: getstatic df.fk : Ljava/lang/String;
    //   2789: iload #8
    //   2791: getstatic fl.aU : I
    //   2794: iconst_2
    //   2795: idiv
    //   2796: iadd
    //   2797: iload #9
    //   2799: getstatic fl.aM : B
    //   2802: iconst_4
    //   2803: idiv
    //   2804: isub
    //   2805: iconst_2
    //   2806: iconst_0
    //   2807: invokevirtual a : (Lbx;Ljava/lang/String;IIIZ)V
    //   2810: iload #9
    //   2812: getstatic fl.aM : B
    //   2815: getstatic ft.ab : I
    //   2818: isub
    //   2819: getstatic ft.ab : I
    //   2822: iconst_4
    //   2823: idiv
    //   2824: iadd
    //   2825: iadd
    //   2826: istore #9
    //   2828: iinc #8, 4
    //   2831: goto -> 2866
    //   2834: aload #7
    //   2836: iload #8
    //   2838: iload #9
    //   2840: aload #6
    //   2842: getfield bC : I
    //   2845: bipush #100
    //   2847: getstatic df.fk : Ljava/lang/String;
    //   2850: invokestatic a : (Lbx;IIIILjava/lang/String;)V
    //   2853: iload #9
    //   2855: getstatic ft.aa : I
    //   2858: iconst_2
    //   2859: iadd
    //   2860: iadd
    //   2861: istore #9
    //   2863: iinc #8, 4
    //   2866: getstatic c.m : Lj;
    //   2869: getfield N : I
    //   2872: invokestatic a : (I)Lo;
    //   2875: aload #7
    //   2877: getstatic c.m : Lj;
    //   2880: getfield g : Ljava/lang/String;
    //   2883: iload #8
    //   2885: iload #9
    //   2887: iconst_0
    //   2888: iconst_0
    //   2889: invokevirtual a : (Lbx;Ljava/lang/String;IIIZ)V
    //   2892: iload #9
    //   2894: iload_2
    //   2895: iadd
    //   2896: istore #9
    //   2898: getstatic c.n : Lj;
    //   2901: getfield N : I
    //   2904: invokestatic a : (I)Lo;
    //   2907: aload #7
    //   2909: getstatic c.n : Lj;
    //   2912: getfield g : Ljava/lang/String;
    //   2915: iload #8
    //   2917: iload #9
    //   2919: iconst_0
    //   2920: iconst_0
    //   2921: invokevirtual a : (Lbx;Ljava/lang/String;IIIZ)V
    //   2924: iload #9
    //   2926: iload_2
    //   2927: iadd
    //   2928: istore #9
    //   2930: getstatic o.j : Lo;
    //   2933: aload #7
    //   2935: getstatic df.fo : Ljava/lang/String;
    //   2938: iload #8
    //   2940: iload #9
    //   2942: iconst_0
    //   2943: iconst_0
    //   2944: invokevirtual a : (Lbx;Ljava/lang/String;IIIZ)V
    //   2947: iload #9
    //   2949: iload_2
    //   2950: iadd
    //   2951: istore #9
    //   2953: getstatic o.f : Lo;
    //   2956: aload #7
    //   2958: new java/lang/StringBuffer
    //   2961: dup
    //   2962: getstatic c.m : Lj;
    //   2965: getfield z : B
    //   2968: iconst_2
    //   2969: isub
    //   2970: invokestatic valueOf : (I)Ljava/lang/String;
    //   2973: invokespecial <init> : (Ljava/lang/String;)V
    //   2976: ldc ' > '
    //   2978: invokevirtual append : (Ljava/lang/String;)Ljava/lang/StringBuffer;
    //   2981: getstatic c.m : Lj;
    //   2984: getfield z : B
    //   2987: invokevirtual append : (I)Ljava/lang/StringBuffer;
    //   2990: invokevirtual toString : ()Ljava/lang/String;
    //   2993: iload #8
    //   2995: iload #9
    //   2997: iconst_0
    //   2998: iconst_0
    //   2999: invokevirtual a : (Lbx;Ljava/lang/String;IIIZ)V
    //   3002: goto -> 3024
    //   3005: aload_2
    //   3006: getfield bv : B
    //   3009: getstatic c.c : B
    //   3012: if_icmpne -> 3024
    //   3015: aload_2
    //   3016: aload_3
    //   3017: iload #4
    //   3019: iload #5
    //   3021: invokespecial a : (Lbx;II)V
    //   3024: getstatic ft.o : Lfq;
    //   3027: getfield a : Z
    //   3030: ifne -> 3109
    //   3033: getstatic ft.r : Lda;
    //   3036: ifnonnull -> 3109
    //   3039: getstatic ft.s : Lda;
    //   3042: ifnonnull -> 3109
    //   3045: getstatic fl.aO : B
    //   3048: iconst_1
    //   3049: if_icmpeq -> 3058
    //   3052: getstatic fl.aU : I
    //   3055: ifle -> 3109
    //   3058: aload_0
    //   3059: getfield bM : Les;
    //   3062: ifnull -> 3109
    //   3065: iconst_0
    //   3066: istore_2
    //   3067: goto -> 3098
    //   3070: aload_0
    //   3071: getfield bM : Les;
    //   3074: iload_2
    //   3075: invokevirtual a : (I)Ljava/lang/Object;
    //   3078: checkcast bt
    //   3081: dup
    //   3082: astore_3
    //   3083: aload_1
    //   3084: aload_3
    //   3085: getfield h : I
    //   3088: aload_3
    //   3089: getfield i : I
    //   3092: invokevirtual a : (Lbx;II)V
    //   3095: iinc #2, 1
    //   3098: iload_2
    //   3099: aload_0
    //   3100: getfield bM : Les;
    //   3103: invokevirtual c : ()I
    //   3106: if_icmplt -> 3070
    //   3109: return
  }
  
  private void b(bx parambx) {
    for (byte b1 = 0; b1 < this.bD.length; b1++) {
      if (ft.B) {
        fl.c(parambx, this.bD[b1][0] - 10, this.bD[b1][1] - 10, 20, 20, 2);
      } else {
        parambx.a(fl.aP[2], 0, 0, 20, 20, 0, this.bD[b1][0], this.bD[b1][1], 3);
      } 
      if (b1 == 6) {
        if (o != null) {
          o.a(parambx, this.bD[6][0], this.bD[6][1], 21, 1, 0);
          if (B == 0)
            o.j.a(parambx, "Lv " + o.z, this.bD[6][0], this.bD[6][1] - 22, 2, false); 
        } 
      } else if (s != null && b1 < s.length && B == 0) {
        j j1;
        if ((j1 = bw.b((s[b1]).a)) != null) {
          j1.a(parambx, this.bD[b1][0], this.bD[b1][1], 21, 0, 0);
          if (r[b1] >= (s[b1]).b) {
            o.j.a(parambx, (s[b1]).b, this.bD[b1][0], this.bD[b1][1] + 11, 2, false);
          } else {
            o.m.a(parambx, (s[b1]).b, this.bD[b1][0], this.bD[b1][1] + 11, 2, false);
          } 
        } else {
          bw.c((s[b1]).a);
        } 
      } 
      parambx.a(cg.ap, this.bD[b1][0], this.bD[b1][1], 3);
    } 
  }
  
  public static void a(j paramj) {
    G.a(paramj);
  }
  
  public static void a(bw parambw) {
    for (byte b1 = 0; b1 < G.c(); b1++) {
      j j1;
      if ((j1 = (j)G.a(b1)) != null && j1.O == parambw.O)
        G.d(j1); 
    } 
  }
  
  public static boolean b(bw parambw) {
    for (byte b1 = 0; b1 < G.c(); b1++) {
      j j1;
      if ((j1 = (j)G.a(b1)) != null && j1.O == parambw.O)
        return true; 
    } 
    return false;
  }
  
  private void a(bx parambx, int paramInt1, int paramInt2) {
    if (s == null)
      return; 
    int i = ft.ab;
    if (fl.aU > 0) {
      fl.a(parambx, paramInt1 + fl.aU / 2, paramInt2 - fl.aM / 4, fl.aU, v, 5);
      paramInt2 += fl.aM - ft.ab + ft.ab / 4;
      paramInt1 += 4;
    } else {
      cg.a(parambx, paramInt1, paramInt2, this.bC, 150, v);
      paramInt2 += ft.aa + 2;
      paramInt1 += 4;
    } 
    o.j.a(parambx, String.valueOf(df.bG) + x, paramInt1, paramInt2, 0, false);
    paramInt2 += i;
    o.j.a(parambx, String.valueOf(df.fu) + cf.a(u), paramInt1, paramInt2, 0, false);
    paramInt2 += i;
    for (byte b1 = 0; b1 < s.length; b1++) {
      j j1;
      if ((j1 = bw.b((s[b1]).a)) != null) {
        o o = o.j;
        if ((s[b1]).b > r[b1])
          o = o.m; 
        if (j1.g != null)
          o.a(parambx, j1.g, paramInt1 + 4, paramInt2, 0, false); 
        o.a(parambx, String.valueOf((s[b1]).b) + "/" + r[b1], paramInt1 + this.bC / 2 + 10, paramInt2, 0, false);
        paramInt2 += i;
      } else {
        bw.c((s[b1]).a);
      } 
    } 
  }
  
  private void b(bx parambx, int paramInt1, int paramInt2) {
    int i = ft.ab - 2;
    if (fl.aU > 0) {
      paramInt2 += fl.aM - ft.ab + ft.ab / 4;
      paramInt1 += 4;
    } else {
      String str = df.bK;
      if (l != null && l.g != null)
        str = l.g; 
      cg.a(parambx, paramInt1, paramInt2, this.bC, 150, str);
      paramInt2 += ft.aa + 2;
      paramInt1 += 4;
    } 
    paramInt2 += i;
    byte b2 = 0;
    if (!ft.A)
      b2 = 20; 
    ft.a(parambx);
    if (ft.A) {
      this.bO.a(G.c() + 2, ft.ab + 2, paramInt1, paramInt2 - (ft.ab << 1), this.bC, i * (G.c() + 2) << 1, true, 1);
      this.bO.a(parambx, paramInt1, paramInt2, this.bC, i * (G.c() + 2) << 1);
    } 
    o.f.a(parambx, df.ed, paramInt1, paramInt2 - b2, 0, false);
    paramInt2 += i;
    for (byte b1 = 0; b1 < G.c(); b1++) {
      j j1;
      if ((j1 = (j)G.a(b1)) != null) {
        o o;
        j j2;
        if ((j2 = bw.b(j1.O)) != null) {
          o = o.o;
          if (j2.g != null && !j2.g.equals(""))
            fl.b(j2.N).a(parambx, j2.g, paramInt1 + 4, paramInt2 - b2, 0, true); 
          if (i[b1] == 0)
            o = o.m; 
          paramInt2 += i;
          o.j.a(parambx, String.valueOf(df.eZ) + " ", paramInt1 + 4, paramInt2 - b2, 0, true);
          o.a(parambx, h[b1], paramInt1 + 50, paramInt2 - b2, 0, true);
          paramInt2 += i;
        } else {
          bw.c(((bw)o).O);
        } 
      } 
    } 
    ft.a(parambx);
  }
  
  private void c(bx parambx, int paramInt1, int paramInt2) {
    // Byte code:
    //   0: getstatic c.l : Lj;
    //   3: ifnonnull -> 7
    //   6: return
    //   7: getstatic ft.ab : I
    //   10: iconst_2
    //   11: isub
    //   12: istore #4
    //   14: getstatic fl.aU : I
    //   17: ifle -> 96
    //   20: getstatic c.l : Lj;
    //   23: getfield g : Ljava/lang/String;
    //   26: ifnull -> 62
    //   29: aload_1
    //   30: iload_2
    //   31: getstatic fl.aU : I
    //   34: iconst_2
    //   35: idiv
    //   36: iadd
    //   37: iload_3
    //   38: getstatic fl.aM : B
    //   41: iconst_4
    //   42: idiv
    //   43: isub
    //   44: getstatic fl.aU : I
    //   47: getstatic c.l : Lj;
    //   50: getfield g : Ljava/lang/String;
    //   53: getstatic c.l : Lj;
    //   56: getfield N : I
    //   59: invokestatic a : (Lbx;IIILjava/lang/String;I)V
    //   62: getstatic c.l : Lj;
    //   65: getfield z : B
    //   68: bipush #15
    //   70: if_icmplt -> 74
    //   73: return
    //   74: iload_3
    //   75: getstatic fl.aM : B
    //   78: getstatic ft.ab : I
    //   81: isub
    //   82: getstatic ft.ab : I
    //   85: iconst_4
    //   86: idiv
    //   87: iadd
    //   88: iadd
    //   89: istore_3
    //   90: iinc #2, 4
    //   93: goto -> 126
    //   96: aload_1
    //   97: iload_2
    //   98: iload_3
    //   99: aload_0
    //   100: getfield bC : I
    //   103: sipush #150
    //   106: getstatic c.l : Lj;
    //   109: getfield g : Ljava/lang/String;
    //   112: invokestatic a : (Lbx;IIIILjava/lang/String;)V
    //   115: iload_3
    //   116: getstatic ft.aa : I
    //   119: iconst_2
    //   120: iadd
    //   121: iadd
    //   122: istore_3
    //   123: iinc #2, 4
    //   126: aload_0
    //   127: getfield bb : Z
    //   130: ifeq -> 284
    //   133: getstatic c.l : Lj;
    //   136: getfield ak : Lbw;
    //   139: ifnonnull -> 143
    //   142: return
    //   143: aconst_null
    //   144: astore #5
    //   146: iconst_0
    //   147: istore #6
    //   149: getstatic o.b : Lo;
    //   152: getstatic c.l : Lj;
    //   155: getfield I : [Ljava/lang/String;
    //   158: iconst_0
    //   159: aaload
    //   160: invokevirtual a : (Ljava/lang/String;)I
    //   163: pop
    //   164: iconst_0
    //   165: istore #7
    //   167: getstatic o.b : Lo;
    //   170: getstatic c.l : Lj;
    //   173: getfield I : [Ljava/lang/String;
    //   176: iconst_0
    //   177: aaload
    //   178: getstatic fl.aU : I
    //   181: ifne -> 195
    //   184: aload_0
    //   185: getfield bz : I
    //   188: iconst_1
    //   189: isub
    //   190: iconst_5
    //   191: ishl
    //   192: goto -> 198
    //   195: getstatic fl.aU : I
    //   198: invokevirtual a : (Ljava/lang/String;I)[Ljava/lang/String;
    //   201: dup
    //   202: astore #5
    //   204: arraylength
    //   205: istore #6
    //   207: iconst_0
    //   208: istore_0
    //   209: goto -> 235
    //   212: getstatic o.b : Lo;
    //   215: aload_1
    //   216: aload #5
    //   218: iload_0
    //   219: aaload
    //   220: iload_2
    //   221: iload_3
    //   222: iconst_0
    //   223: iconst_0
    //   224: invokevirtual a : (Lbx;Ljava/lang/String;IIIZ)V
    //   227: iload_3
    //   228: iload #4
    //   230: iadd
    //   231: istore_3
    //   232: iinc #0, 1
    //   235: iload_0
    //   236: iload #6
    //   238: if_icmplt -> 212
    //   241: getstatic o.f : Lo;
    //   244: aload_1
    //   245: getstatic df.ec : Ljava/lang/String;
    //   248: iload_2
    //   249: iload_3
    //   250: iconst_0
    //   251: iconst_0
    //   252: invokevirtual a : (Lbx;Ljava/lang/String;IIIZ)V
    //   255: iload_3
    //   256: iload #4
    //   258: iconst_2
    //   259: isub
    //   260: iadd
    //   261: istore_3
    //   262: getstatic o.j : Lo;
    //   265: aload_1
    //   266: getstatic c.l : Lj;
    //   269: getfield I : [Ljava/lang/String;
    //   272: iconst_1
    //   273: aaload
    //   274: iload_2
    //   275: iconst_4
    //   276: iadd
    //   277: iload_3
    //   278: iconst_0
    //   279: iconst_0
    //   280: invokevirtual a : (Lbx;Ljava/lang/String;IIIZ)V
    //   283: return
    //   284: getstatic c.l : Lj;
    //   287: getfield z : B
    //   290: bipush #15
    //   292: if_icmpge -> 343
    //   295: getstatic o.b : Lo;
    //   298: aload_1
    //   299: new java/lang/StringBuffer
    //   302: dup
    //   303: ldc '+'
    //   305: invokespecial <init> : (Ljava/lang/String;)V
    //   308: getstatic c.l : Lj;
    //   311: getfield z : B
    //   314: invokevirtual append : (I)Ljava/lang/StringBuffer;
    //   317: ldc ' > +'
    //   319: invokevirtual append : (Ljava/lang/String;)Ljava/lang/StringBuffer;
    //   322: getstatic c.l : Lj;
    //   325: getfield z : B
    //   328: iconst_1
    //   329: iadd
    //   330: invokevirtual append : (I)Ljava/lang/StringBuffer;
    //   333: invokevirtual toString : ()Ljava/lang/String;
    //   336: iload_2
    //   337: iload_3
    //   338: iconst_0
    //   339: iconst_0
    //   340: invokevirtual a : (Lbx;Ljava/lang/String;IIIZ)V
    //   343: iload_3
    //   344: iload #4
    //   346: iadd
    //   347: istore_3
    //   348: getstatic o.f : Lo;
    //   351: aload_1
    //   352: getstatic df.ed : Ljava/lang/String;
    //   355: iload_2
    //   356: iload_3
    //   357: iconst_0
    //   358: iconst_0
    //   359: invokevirtual a : (Lbx;Ljava/lang/String;IIIZ)V
    //   362: iload_3
    //   363: iload #4
    //   365: iadd
    //   366: istore_3
    //   367: iconst_0
    //   368: istore #5
    //   370: goto -> 544
    //   373: getstatic o.j : Lo;
    //   376: astore #6
    //   378: getstatic c.k : [Lb;
    //   381: getstatic c.l : Lj;
    //   384: getfield z : B
    //   387: aaload
    //   388: getfield e : [B
    //   391: iload #5
    //   393: baload
    //   394: getstatic c.p : [I
    //   397: iload #5
    //   399: iaload
    //   400: if_icmple -> 408
    //   403: getstatic o.m : Lo;
    //   406: astore #6
    //   408: getstatic c.q : [S
    //   411: iload #5
    //   413: saload
    //   414: invokestatic b : (I)Lj;
    //   417: dup
    //   418: astore #7
    //   420: ifnull -> 437
    //   423: getstatic c.j : [Ljava/lang/String;
    //   426: iload #5
    //   428: aload #7
    //   430: getfield g : Ljava/lang/String;
    //   433: aastore
    //   434: goto -> 446
    //   437: getstatic c.q : [S
    //   440: iload #5
    //   442: saload
    //   443: invokestatic c : (I)V
    //   446: getstatic c.j : [Ljava/lang/String;
    //   449: iload #5
    //   451: aaload
    //   452: ifnull -> 473
    //   455: aload #6
    //   457: aload_1
    //   458: getstatic c.j : [Ljava/lang/String;
    //   461: iload #5
    //   463: aaload
    //   464: iload_2
    //   465: iconst_4
    //   466: iadd
    //   467: iload_3
    //   468: iconst_0
    //   469: iconst_0
    //   470: invokevirtual a : (Lbx;Ljava/lang/String;IIIZ)V
    //   473: aload #6
    //   475: aload_1
    //   476: new java/lang/StringBuffer
    //   479: dup
    //   480: getstatic c.k : [Lb;
    //   483: getstatic c.l : Lj;
    //   486: getfield z : B
    //   489: aaload
    //   490: getfield e : [B
    //   493: iload #5
    //   495: baload
    //   496: invokestatic valueOf : (I)Ljava/lang/String;
    //   499: invokespecial <init> : (Ljava/lang/String;)V
    //   502: ldc '/'
    //   504: invokevirtual append : (Ljava/lang/String;)Ljava/lang/StringBuffer;
    //   507: getstatic c.p : [I
    //   510: iload #5
    //   512: iaload
    //   513: invokevirtual append : (I)Ljava/lang/StringBuffer;
    //   516: invokevirtual toString : ()Ljava/lang/String;
    //   519: iload_2
    //   520: aload_0
    //   521: getfield bC : I
    //   524: iconst_2
    //   525: idiv
    //   526: iadd
    //   527: bipush #10
    //   529: iadd
    //   530: iload_3
    //   531: iconst_0
    //   532: iconst_0
    //   533: invokevirtual a : (Lbx;Ljava/lang/String;IIIZ)V
    //   536: iload_3
    //   537: iload #4
    //   539: iadd
    //   540: istore_3
    //   541: iinc #5, 1
    //   544: iload #5
    //   546: getstatic c.k : [Lb;
    //   549: getstatic c.l : Lj;
    //   552: getfield z : B
    //   555: aaload
    //   556: getfield e : [B
    //   559: arraylength
    //   560: if_icmplt -> 373
    //   563: getstatic o.f : Lo;
    //   566: aload_1
    //   567: getstatic df.ee : Ljava/lang/String;
    //   570: iload_2
    //   571: iload_3
    //   572: iconst_0
    //   573: iconst_0
    //   574: invokevirtual a : (Lbx;Ljava/lang/String;IIIZ)V
    //   577: iload_3
    //   578: iload #4
    //   580: iadd
    //   581: istore_3
    //   582: getstatic o.j : Lo;
    //   585: aload_1
    //   586: getstatic c.z : Ljava/lang/String;
    //   589: iload_2
    //   590: iconst_4
    //   591: iadd
    //   592: iload_3
    //   593: iconst_0
    //   594: iconst_0
    //   595: invokevirtual a : (Lbx;Ljava/lang/String;IIIZ)V
    //   598: iload_3
    //   599: iload #4
    //   601: iadd
    //   602: istore_3
    //   603: getstatic o.f : Lo;
    //   606: aload_1
    //   607: getstatic df.ec : Ljava/lang/String;
    //   610: iload_2
    //   611: iload_3
    //   612: iconst_0
    //   613: iconst_0
    //   614: invokevirtual a : (Lbx;Ljava/lang/String;IIIZ)V
    //   617: iload_3
    //   618: iload #4
    //   620: iconst_2
    //   621: isub
    //   622: iadd
    //   623: istore_3
    //   624: aload_1
    //   625: iload_2
    //   626: iload_3
    //   627: istore_2
    //   628: istore_1
    //   629: astore_0
    //   630: getstatic c.k : [Lb;
    //   633: getstatic c.l : Lj;
    //   636: getfield z : B
    //   639: aaload
    //   640: getfield c : I
    //   643: ifne -> 697
    //   646: getstatic o.j : Lo;
    //   649: aload_0
    //   650: new java/lang/StringBuffer
    //   653: dup
    //   654: getstatic c.k : [Lb;
    //   657: getstatic c.l : Lj;
    //   660: getfield z : B
    //   663: aaload
    //   664: getfield d : I
    //   667: invokestatic valueOf : (I)Ljava/lang/String;
    //   670: invokespecial <init> : (Ljava/lang/String;)V
    //   673: ldc ' '
    //   675: invokevirtual append : (Ljava/lang/String;)Ljava/lang/StringBuffer;
    //   678: getstatic df.bP : Ljava/lang/String;
    //   681: invokevirtual append : (Ljava/lang/String;)Ljava/lang/StringBuffer;
    //   684: invokevirtual toString : ()Ljava/lang/String;
    //   687: iload_1
    //   688: iconst_4
    //   689: iadd
    //   690: iload_2
    //   691: iconst_0
    //   692: iconst_0
    //   693: invokevirtual a : (Lbx;Ljava/lang/String;IIIZ)V
    //   696: return
    //   697: getstatic c.k : [Lb;
    //   700: getstatic c.l : Lj;
    //   703: getfield z : B
    //   706: aaload
    //   707: getfield d : I
    //   710: ifne -> 764
    //   713: getstatic o.j : Lo;
    //   716: aload_0
    //   717: new java/lang/StringBuffer
    //   720: dup
    //   721: getstatic c.k : [Lb;
    //   724: getstatic c.l : Lj;
    //   727: getfield z : B
    //   730: aaload
    //   731: getfield c : I
    //   734: invokestatic valueOf : (I)Ljava/lang/String;
    //   737: invokespecial <init> : (Ljava/lang/String;)V
    //   740: ldc ' '
    //   742: invokevirtual append : (Ljava/lang/String;)Ljava/lang/StringBuffer;
    //   745: getstatic df.bO : Ljava/lang/String;
    //   748: invokevirtual append : (Ljava/lang/String;)Ljava/lang/StringBuffer;
    //   751: invokevirtual toString : ()Ljava/lang/String;
    //   754: iload_1
    //   755: iconst_4
    //   756: iadd
    //   757: iload_2
    //   758: iconst_0
    //   759: iconst_0
    //   760: invokevirtual a : (Lbx;Ljava/lang/String;IIIZ)V
    //   763: return
    //   764: getstatic o.j : Lo;
    //   767: aload_0
    //   768: new java/lang/StringBuffer
    //   771: dup
    //   772: getstatic c.k : [Lb;
    //   775: getstatic c.l : Lj;
    //   778: getfield z : B
    //   781: aaload
    //   782: getfield c : I
    //   785: invokestatic valueOf : (I)Ljava/lang/String;
    //   788: invokespecial <init> : (Ljava/lang/String;)V
    //   791: ldc ' '
    //   793: invokevirtual append : (Ljava/lang/String;)Ljava/lang/StringBuffer;
    //   796: getstatic df.bO : Ljava/lang/String;
    //   799: invokevirtual append : (Ljava/lang/String;)Ljava/lang/StringBuffer;
    //   802: getstatic df.ef : Ljava/lang/String;
    //   805: invokevirtual append : (Ljava/lang/String;)Ljava/lang/StringBuffer;
    //   808: getstatic c.k : [Lb;
    //   811: getstatic c.l : Lj;
    //   814: getfield z : B
    //   817: aaload
    //   818: getfield d : I
    //   821: invokevirtual append : (I)Ljava/lang/StringBuffer;
    //   824: ldc ' '
    //   826: invokevirtual append : (Ljava/lang/String;)Ljava/lang/StringBuffer;
    //   829: getstatic df.bP : Ljava/lang/String;
    //   832: invokevirtual append : (Ljava/lang/String;)Ljava/lang/StringBuffer;
    //   835: invokevirtual toString : ()Ljava/lang/String;
    //   838: iload_1
    //   839: iconst_4
    //   840: iadd
    //   841: iload_2
    //   842: iconst_0
    //   843: iconst_0
    //   844: invokevirtual a : (Lbx;Ljava/lang/String;IIIZ)V
    //   847: return
  }
  
  private void e(bx parambx) {
    for (byte b1 = 0; b1 < this.bD.length; b1++) {
      if (ft.B) {
        fl.c(parambx, this.bD[b1][0] - 10, this.bD[b1][1] - 10, 20, 20, 2);
      } else {
        parambx.a(fl.aP[2], 0, 0, 20, 20, 0, this.bD[b1][0], this.bD[b1][1], 3);
      } 
      if (m != null && b1 == 0) {
        m.a(parambx, this.bD[0][0], this.bD[0][1], 21, 1, 0);
        if (B == 0)
          o.j.a(parambx, "Lv " + m.z, this.bD[0][0], this.bD[0][1] - 22, 2, false); 
      } 
      if (n != null && b1 == 1) {
        n.a(parambx, this.bD[1][0], this.bD[1][1], 21, 1, 0);
        if (B == 0)
          o.j.a(parambx, "Lv " + n.z, this.bD[1][0], this.bD[1][1] - 22, 2, false); 
      } 
      parambx.a(cg.ap, this.bD[b1][0], this.bD[b1][1], 3);
    } 
  }
  
  public final void d() {
    if (B != 0)
      return; 
    if (ft.al[4] || ft.al[6]) {
      fl.aO = 0;
      ft.m();
    } 
    super.d();
  }
  
  public final void a() {
    if (this.bv == 0) {
      c c1 = this;
      if (bN && B == 2) {
        B = C;
        c1.bQ = 0L;
      } 
      if (B == 1) {
        if (fl.aU == 0)
          bG = false; 
        ft.j();
        if (!ft.A) {
          c1.Y = null;
          c1.aa = null;
        } else {
          c1.bM.d();
        } 
        if (l != null) {
          E.d();
          for (byte b2 = 0; b2 < (k[l.z]).e.length; b2++) {
            if ((k[l.z]).e[b2] > 0)
              a(31, c1.bD[b2][0], c1.bD[b2][1], c1.bD[5][0], c1.bD[5][1], 1); 
          } 
          if (D)
            a(31, c1.bD[4][0], c1.bD[4][1], c1.bD[5][0], c1.bD[5][1], 1); 
        } 
        B = 2;
        c1.bQ = 0L;
      } else if (B == 2) {
        if (c1.bQ < 10L) {
          c1.bQ++;
          if (c1.bQ == 10L);
        } else {
          if (ft.aj - c1.bQ > 12000L) {
            c1.bQ = ft.aj;
            a(29, c1.bD[5][0], c1.bD[5][1], 12100);
          } 
          if (ft.aj - c1.bQ > 3700L && (C == 3 || C == 4)) {
            B = C;
            c1.bQ = 0L;
          } 
        } 
      } else if (B == 3) {
        E.d();
        a(32, c1.bD[5][0], c1.bD[5][1] - 11);
        a(33, c1.bD[5][0], c1.bD[5][1]);
        a(34, c1.bD[5][0], c1.bD[5][1]);
        B = 5;
        c1.bQ = 0L;
      } else if (B == 4) {
        E.d();
        a(11, c1.bD[5][0], c1.bD[5][1]);
        a(69, c1.bD[5][0], c1.bD[5][1] - 11, 300);
        a(69, c1.bD[5][0], c1.bD[5][1] - 11, 300);
        B = 5;
        c1.bQ = 0L;
      } else if (B == 5) {
        c1.bQ++;
        j j1 = (j)bw.a(l.u, (short)l.O);
        if (!c1.bb)
          if (j1 != null) {
            l = j.a(j1.O, j1.i, j1.t, j1.z, j1.N, j1.M, j1.u, j1.j, j1.R, false, j1.v, j1.q, (short)j1.S, j1.x, j1.y, j1.p, (byte)0, (byte)0);
          } else {
            l = null;
          }  
        z = A;
        if (E.c() == 0 || c1.bQ >= 100L) {
          if (!bN) {
            ft.o.a(null, F, fq.f, (byte)2, false, 0);
          } else if (C == 3) {
            ft.c(df.f);
          } else if (C == 4) {
            ft.c(df.g);
          } 
          c1.bQ = 0L;
          B = 6;
        } 
      } else if (B == 6) {
        bN = false;
        if (l.z == 15)
          l = null; 
        if (c1.bb && l != null)
          l = null; 
        B = 0;
        if (D)
          for (byte b2 = 0;; b2++) {
            if (b2 >= bw.V.c()) {
              D = false;
              break;
            } 
            j j1;
            if ((j1 = (j)bw.V.a(b2)).u == 7 && j1.A == 11 && I != null && I.O == j1.O) {
              q.a().b((byte)0, (short)j1.O, (byte)j1.u);
              break;
            } 
          }  
        if (!ft.A) {
          c1.Y = c1.bI;
          c1.aa = c1.bH;
          fl.aO = 0;
        } else {
          c1.bM.d();
          if (l != null)
            if (fl.aU > 0) {
              c1.bM.a(c1.bH);
            } else {
              c1.bM.a(c1.bI);
              c1.bM.a(c1.bH);
            }  
        } 
      } 
      if (this.bb) {
        this.bH.a = df.gd;
        this.bH.e = 7;
      } else {
        this.bH.a = df.eg;
        this.bH.e = 0;
      } 
    } else if (this.bv == b) {
      c c1 = this;
      if (B == 1) {
        if (m == null || n == null) {
          B = 0;
        } else {
          if (fl.aU == 0)
            bG = false; 
          ft.j();
          if (!ft.A) {
            c1.Y = null;
            c1.aa = null;
          } else {
            c1.bM.d();
          } 
          E.d();
          a(37, c1.bD[0][0], c1.bD[0][1], c1.bD[1][0], c1.bD[1][1], m.z);
          c1.bP = m.z * 120;
          B = 2;
          c1.bQ = 0L;
        } 
      } else if (B == 2) {
        if (c1.bQ < 10L) {
          c1.bQ++;
          if (c1.bQ == 10L);
        } else {
          if (c1.bQ == 10L) {
            c1.bQ = ft.aj;
            a(29, c1.bD[1][0], c1.bD[1][1], 1200 + c1.bP);
          } 
          if (ft.aj - c1.bQ > (2000 + c1.bP)) {
            E.d();
            B = 3;
            c1.bQ = 0L;
          } 
        } 
      } else if (B == 3) {
        ft.o.a(null, F, fq.f, (byte)2, false, 0);
        if (m != null) {
          j j1;
          if ((j1 = (j)bw.a(m.u, (short)m.O)) != null) {
            m = j.a(j1.O, j1.i, j1.t, j1.z, j1.N, j1.M, j1.u, j1.j, j1.R, false, j1.v, j1.q, (short)j1.S, j1.x, j1.y, j1.p, (byte)0, (byte)0);
          } else {
            m = null;
          } 
        } 
        if (n != null) {
          j j1;
          if ((j1 = (j)bw.a(n.u, (short)n.O)) != null) {
            n = j.a(j1.O, j1.i, j1.t, j1.z, j1.N, j1.M, j1.u, j1.j, j1.R, false, j1.v, j1.q, (short)j1.S, j1.x, j1.y, j1.p, (byte)0, (byte)0);
          } else {
            n = null;
          } 
        } 
        B = 0;
        H = true;
        c1.bM.d();
        bG = false;
        c1.aa = null;
        c1.Y = null;
      } 
    } else if (this.bv == c) {
      c c1 = this;
      if (B == 1) {
        if (fl.aU == 0)
          bG = false; 
        ft.j();
        if (!ft.A) {
          c1.Y = null;
          c1.aa = null;
        } else {
          c1.bM.d();
        } 
        if (s != null) {
          E.d();
          for (byte b2 = 0; b2 < s.length; b2++)
            a(31, c1.bD[b2][0], c1.bD[b2][1], c1.bD[6][0], c1.bD[6][1], 1); 
        } 
        B = 2;
        c1.bQ = 0L;
      } else if (B == 2) {
        if (c1.bQ < 10L) {
          c1.bQ++;
          if (c1.bQ == 10L);
        } else {
          if (ft.aj - c1.bQ > 12000L) {
            c1.bQ = ft.aj;
            a(29, c1.bD[6][0], c1.bD[6][1], 12100);
          } 
          if (ft.aj - c1.bQ > 3700L) {
            B = 3;
            c1.bQ = 0L;
          } 
        } 
      } else if (B == 3) {
        E.d();
        if (o != null)
          a(32, c1.bD[6][0], c1.bD[6][1] - 11); 
        a(33, c1.bD[6][0], c1.bD[6][1]);
        a(34, c1.bD[6][0], c1.bD[6][1]);
        B = 5;
        c1.bQ = 0L;
      } else if (B == 5) {
        c1.bQ++;
        j j1;
        if ((j1 = (j)bw.a(3, y)) != null) {
          o = j.a(j1.O, j1.i, j1.t, j1.z, j1.N, j1.M, j1.u, j1.j, j1.R, false, j1.v, j1.q, (short)j1.S, j1.x, j1.y, j1.p, (byte)0, (byte)0);
        } else {
          o = null;
        } 
        if (E.c() == 0 || c1.bQ >= 100L) {
          ft.o.a(null, F, fq.f, (byte)2, false, 0);
          c1.bQ = 0L;
          B = 6;
        } 
      } else if (B == 6) {
        s = null;
        H = true;
        B = 0;
        if (!ft.A) {
          c1.Y = null;
          c1.aa = null;
          fl.aO = 0;
        } else {
          c1.bM.d();
        } 
      } 
    } else if (this.bv == d) {
      c c1 = this;
      if (l != null && J > 0)
        c1.f(); 
      if (J > 0)
        J = (byte)(J - 1); 
      if (B == 1) {
        if (fl.aU == 0)
          bG = false; 
        ft.j();
        if (!ft.A) {
          c1.Y = null;
          c1.aa = null;
        } else {
          c1.bM.d();
        } 
        if (l != null) {
          E.d();
          byte b2;
          if ((b2 = l.z) > 14)
            b2 = 14; 
          for (byte b3 = 0; b3 < (k[b2]).e.length; b3++) {
            if ((k[b2]).e[b3] > 0)
              a(31, c1.bD[b3][0], c1.bD[b3][1], c1.bD[5][0], c1.bD[5][1], 1); 
          } 
          if (D)
            a(31, c1.bD[4][0], c1.bD[4][1], c1.bD[5][0], c1.bD[5][1], 1); 
        } 
        B = 2;
        c1.bQ = 0L;
      } else if (B == 2) {
        if (c1.bQ < 10L) {
          c1.bQ++;
          if (c1.bQ == 10L);
        } else {
          if (ft.aj - c1.bQ > 12000L) {
            c1.bQ = ft.aj;
            a(29, c1.bD[5][0], c1.bD[5][1], 12100);
          } 
          if (ft.aj - c1.bQ > 3700L && (C == 3 || C == 4)) {
            B = C;
            c1.bQ = 0L;
          } 
        } 
      } else if (B == 3) {
        E.d();
        a(32, c1.bD[5][0], c1.bD[5][1] - 11);
        a(33, c1.bD[5][0], c1.bD[5][1]);
        a(34, c1.bD[5][0], c1.bD[5][1]);
        B = 5;
        c1.bQ = 0L;
      } else if (B == 4) {
        E.d();
        a(11, c1.bD[5][0], c1.bD[5][1]);
        a(69, c1.bD[5][0], c1.bD[5][1] - 11, 300);
        a(69, c1.bD[5][0], c1.bD[5][1] - 11, 300);
        B = 5;
        c1.bQ = 0L;
      } else if (B == 5) {
        c1.bQ++;
        j j1 = (j)bw.a(l.u, (short)l.O);
        if (!c1.bb)
          if (j1 != null) {
            l = j.a(j1.O, j1.i, j1.t, j1.z, j1.N, j1.M, j1.u, j1.j, j1.R, false, j1.v, j1.q, (short)j1.S, j1.x, j1.y, j1.p, (byte)0, (byte)0);
          } else {
            l = null;
          }  
        z = A;
        if (E.c() == 0 || c1.bQ >= 100L) {
          ft.o.a(null, F, fq.f, (byte)2, false, 0);
          c1.bQ = 0L;
          B = 6;
        } 
        J = 1;
      } else if (B == 6) {
        if (l.z == 15)
          l = null; 
        if (c1.bb && l != null)
          l = null; 
        B = 0;
        if (!ft.A) {
          c1.Y = c1.bI;
          c1.aa = c1.bH;
          fl.aO = 0;
        } else {
          c1.bM.d();
          if (l != null)
            if (fl.aU > 0) {
              c1.bM.a(c1.bH);
            } else {
              c1.bM.a(c1.bI);
              c1.bM.a(c1.bH);
            }  
        } 
      } 
      this.bH.a = df.Q;
      this.bH.e = 0;
    } else if (this.bv == e) {
      c c1 = this;
      if (B == 1) {
        if (fl.aU == 0)
          bG = false; 
        ft.j();
        if (!ft.A) {
          c1.Y = null;
          c1.aa = null;
        } else {
          c1.bM.d();
        } 
        if (l != null) {
          E.d();
          for (byte b2 = 0; b2 < (k[l.z]).e.length; b2++) {
            if ((k[l.z]).e[b2] > 0)
              a(31, c1.bD[b2][0], c1.bD[b2][1], c1.bD[5][0], c1.bD[5][1], 1); 
          } 
          if (D)
            a(31, c1.bD[4][0], c1.bD[4][1], c1.bD[5][0], c1.bD[5][1], 1); 
        } 
        B = 2;
        c1.bQ = 0L;
      } else if (B == 2) {
        if (c1.bQ < 10L) {
          c1.bQ++;
          if (c1.bQ == 10L);
        } else {
          if (ft.aj - c1.bQ > 12000L) {
            c1.bQ = ft.aj;
            a(29, c1.bD[5][0], c1.bD[5][1], 12100);
          } 
          if (ft.aj - c1.bQ > 3700L && (C == 3 || C == 4)) {
            B = C;
            c1.bQ = 0L;
          } 
        } 
      } else if (B == 3) {
        E.d();
        a(32, c1.bD[5][0], c1.bD[5][1] - 11);
        a(33, c1.bD[5][0], c1.bD[5][1]);
        a(34, c1.bD[5][0], c1.bD[5][1]);
        B = 5;
        c1.bQ = 0L;
      } else if (B == 5) {
        c1.bQ++;
        if (E.c() == 0 || c1.bQ >= 100L) {
          ft.o.a(null, F, fq.f, (byte)2, false, 0);
          c1.bQ = 0L;
          B = 6;
        } 
      } else if (B == 6) {
        if (l.z == 15)
          l = null; 
        if (c1.bb && l != null)
          l = null; 
        B = 0;
        if (!ft.A) {
          c1.Y = c1.bI;
          c1.aa = c1.bH;
          fl.aO = 0;
        } else {
          c1.bM.d();
          if (l != null)
            if (fl.aU > 0) {
              c1.bM.a(c1.bH);
            } else {
              c1.bM.a(c1.bI);
              c1.bM.a(c1.bH);
            }  
        } 
      } 
      this.bH.a = df.L;
      this.bH.e = 0;
    } else if (this.bv == f) {
      c c1 = this;
      if (l != null && J > 0)
        c1.f(); 
      if (J > 0)
        J = (byte)(J - 1); 
      if (B == 1) {
        if (fl.aU == 0)
          bG = false; 
        ft.j();
        if (!ft.A) {
          c1.Y = null;
          c1.aa = null;
        } else {
          c1.bM.d();
        } 
        if (l != null) {
          E.d();
          byte b2;
          if ((b2 = l.z) > 14)
            b2 = 14; 
          for (byte b3 = 0; b3 < (k[b2]).e.length; b3++) {
            if ((k[b2]).e[b3] > 0)
              a(31, c1.bD[b3][0], c1.bD[b3][1], c1.bD[5][0], c1.bD[5][1], 1); 
          } 
          if (D)
            a(31, c1.bD[4][0], c1.bD[4][1], c1.bD[5][0], c1.bD[5][1], 1); 
        } 
        B = 2;
        c1.bQ = 0L;
      } else if (B == 2) {
        if (c1.bQ < 10L) {
          c1.bQ++;
          if (c1.bQ == 10L);
        } else {
          if (ft.aj - c1.bQ > 12000L) {
            c1.bQ = ft.aj;
            a(29, c1.bD[5][0], c1.bD[5][1], 12100);
          } 
          if (ft.aj - c1.bQ > 3700L && (C == 3 || C == 4)) {
            B = C;
            c1.bQ = 0L;
          } 
        } 
      } else if (B == 3) {
        E.d();
        a(32, c1.bD[5][0], c1.bD[5][1] - 11);
        a(33, c1.bD[5][0], c1.bD[5][1]);
        a(34, c1.bD[5][0], c1.bD[5][1]);
        B = 5;
        c1.bQ = 0L;
      } else if (B == 4) {
        E.d();
        a(11, c1.bD[5][0], c1.bD[5][1]);
        a(69, c1.bD[5][0], c1.bD[5][1] - 11, 300);
        a(69, c1.bD[5][0], c1.bD[5][1] - 11, 300);
        B = 5;
        c1.bQ = 0L;
      } else if (B == 5) {
        c1.bQ++;
        j j1 = (j)bw.a(l.u, (short)l.O);
        if (!c1.bb)
          if (j1 != null) {
            l = j.a(j1.O, j1.i, j1.t, j1.z, j1.N, j1.M, j1.u, j1.j, j1.R, false, j1.v, j1.q, (short)j1.S, j1.x, j1.y, j1.p, (byte)0, (byte)0);
          } else {
            l = null;
          }  
        z = A;
        if (E.c() == 0 || c1.bQ >= 100L) {
          ft.o.a(null, F, fq.f, (byte)2, false, 0);
          c1.bQ = 0L;
          B = 6;
        } 
        J = 1;
      } else if (B == 6) {
        if (l.z == 15)
          l = null; 
        if (c1.bb && l != null)
          l = null; 
        B = 0;
        if (!ft.A) {
          c1.Y = c1.bI;
          c1.aa = c1.bH;
          fl.aO = 0;
        } else {
          c1.bM.d();
          if (l != null)
            if (fl.aU > 0) {
              c1.bM.a(c1.bH);
            } else {
              c1.bM.a(c1.bI);
              c1.bM.a(c1.bH);
            }  
        } 
      } 
      this.bH.a = df.I;
      this.bH.e = 0;
    } else if (this.bv == g) {
      c c1 = this;
      if (l != null && J > 0)
        c1.f(); 
      if (J > 0)
        J = (byte)(J - 1); 
      if (B == 1) {
        if (fl.aU == 0)
          bG = false; 
        ft.j();
        if (!ft.A) {
          c1.Y = null;
          c1.aa = null;
        } else {
          c1.bM.d();
        } 
        if (l != null) {
          E.d();
          byte b2;
          if ((b2 = l.z) > 14)
            b2 = 14; 
          for (byte b3 = 0; b3 < (k[b2]).e.length; b3++) {
            if ((k[b2]).e[b3] > 0)
              a(31, c1.bD[b3][0], c1.bD[b3][1], c1.bD[5][0], c1.bD[5][1], 1); 
          } 
          if (D)
            a(31, c1.bD[4][0], c1.bD[4][1], c1.bD[5][0], c1.bD[5][1], 1); 
        } 
        B = 2;
        c1.bQ = 0L;
      } else if (B == 2) {
        if (c1.bQ < 10L) {
          c1.bQ++;
          if (c1.bQ == 10L);
        } else {
          if (ft.aj - c1.bQ > 12000L) {
            c1.bQ = ft.aj;
            a(29, c1.bD[5][0], c1.bD[5][1], 12100);
          } 
          if (ft.aj - c1.bQ > 3700L && (C == 3 || C == 4)) {
            B = C;
            c1.bQ = 0L;
          } 
        } 
      } else if (B == 3) {
        E.d();
        a(32, c1.bD[5][0], c1.bD[5][1] - 11);
        a(33, c1.bD[5][0], c1.bD[5][1]);
        a(34, c1.bD[5][0], c1.bD[5][1]);
        B = 5;
        c1.bQ = 0L;
      } else if (B == 4) {
        E.d();
        a(11, c1.bD[5][0], c1.bD[5][1]);
        a(69, c1.bD[5][0], c1.bD[5][1] - 11, 300);
        a(69, c1.bD[5][0], c1.bD[5][1] - 11, 300);
        B = 5;
        c1.bQ = 0L;
      } else if (B == 5) {
        c1.bQ++;
        if (E.c() == 0 || c1.bQ >= 100L) {
          ft.o.a(null, F, fq.f, (byte)2, false, 0);
          c1.bQ = 0L;
          B = 6;
        } 
      } else if (B == 6) {
        if (l.z == 15)
          l = null; 
        if (c1.bb && l != null)
          l = null; 
        B = 0;
        if (!ft.A) {
          c1.Y = c1.bI;
          c1.aa = c1.bH;
          fl.aO = 0;
        } else {
          c1.bM.d();
          if (l != null)
            if (fl.aU > 0) {
              c1.bM.a(c1.bH);
            } else {
              c1.bM.a(c1.bI);
              c1.bM.a(c1.bH);
            }  
        } 
      } 
      cq cq;
      if (!(cq = this.bO.a()).a)
        cq.getClass(); 
      this.bO.b();
      this.bH.a = df.s;
      this.bH.e = 0;
    } 
    for (byte b1 = 0; b1 < E.c(); b1++) {
      dx dx;
      (dx = (dx)E.a(b1)).a();
      if (this.y)
        E.d(this); 
    } 
  }
  
  public final void e() {
    if (B != 0)
      return; 
    if (this.bM != null && !ft.o.a && ft.r == null && ft.s == null && (fl.aO == 1 || fl.aU > 0))
      for (byte b1 = 0; b1 < this.bM.c(); b1++) {
        bt bt1;
        (bt1 = (bt)this.bM.a(b1)).b();
      }  
    super.e();
  }
  
  public static void a(int paramInt1, int paramInt2, int paramInt3, int paramInt4, int paramInt5, int paramInt6) {
    cx cx = new cx(paramInt1, paramInt2, paramInt3, paramInt4, paramInt5, paramInt6);
    E.a(cx);
  }
  
  public static void a(int paramInt1, int paramInt2, int paramInt3) {
    cx cx = new cx(paramInt1, paramInt2, paramInt3);
    E.a(cx);
  }
  
  private static void a(int paramInt1, int paramInt2, int paramInt3, int paramInt4) {
    i i = new i(paramInt1, paramInt2, paramInt3, paramInt4, (short)0, (byte)0);
    E.a(i);
  }
}


/* Location:              C:\Users\Administrator\Desktop\HsoMobi.jar!\c.class
 * Java compiler version: 1 (45.3)
 * JD-Core Version:       1.1.3
 */